Workbook
Name AA.AlternatePriceSourceStartPeriod: "Q1-2018"
Name AA.ColorizerVersion: "2.0.4.0"
Name AA.CompareQuarters.LatestMRQ: "Q1-2019"
Name AA.CSIN: "3PODK70133"
Name AA.DBMacroVersion: "1.0.13.0"
Name AA.FRC.LatestRunOnModelVersion: "FY2018.20"
Name AA.FreeCashFlow: "TRUE"
Name AA.HardcodeChecker.LatestMRQ: "Q3-2019"
Name AA.ModelChecks.LatestMRQ: "FY2021"
Name AA.ModelChecks.LatestVersionNumber: "2.42.15.0"
Name AA.ModelColorScheme: "Classic"
Name AA.ModelVersion: "FY2022.26"
Name AA.PartialUpdate.BsAvailable: "TRUE"
Name AA.PartialUpdate.CfsAvailable: "TRUE"
Name AA.PartialUpdate.IsAvailable: "TRUE"
Name AA.PeriodLayout: "QFY"
Name AA.PersonalMacro.VersionNumber: "1.5.1.5"
Name AA.RowNameEnforcerVersion: "1.0.0.0"
Name AA.SessionToUploadId: ""
Name AA.StartWorkModelVersion: "FY2022.23"
Name AA.StartWorkType: ""
Name AA.SubyearType: "Q"
Name AA.TemplateUpgradeAttempted: "TRUE"
Name AA.TemplateVersion: "7.4.4.0"
Name AA.UpdateType: "Regular"
Name CIRC: Cover!#REF!
Name CIRC2: Cover!#REF!
Name FP.DataSourceName: '[1]Front Page'!$H$15
Name FP.LastPrice: '[1]Front Page'!$H$20
Name FP.LastPriceDate: '[1]Front Page'!$F$20
Name FP.RealTimeToggle: '[1]Front Page'!$H$18
Name HP.MRFX: #REF!
Name HP.ReportCurrency: #REF!
Name HP.Ticker: #REF!
Name HP.TradeCurrency: #REF!
Name HP.TradeCurrency.HardCoded: #REF!
Name IQ_CH: 110000
Name IQ_CQ: 5000
Name IQ_CY: 10000
Name IQ_DAILY: 500000
Name IQ_FH: 100000
Name IQ_FQ: 500
Name IQ_FY: 1000
Name IQ_LTM: 2000
Name IQ_MONTH: 15000
Name IQ_NTM: 6000
Name IQ_WEEK: 50000
Name IQ_YTD: 3000
Name L: '[2]Transaction Assumptions'!$J$20
Name MO_AN_DA: #REF!
Name MO_AN_EBITDA_Adj: #REF!
Name MO_AN_NI_NONGAAP_Diluted: #REF!
Name MO_AN_SBC: #REF!
Name MO_BS_AccComp_Current: #REF!
Name MO_BS_APandAE: #REF!
Name MO_BS_AR: #REF!
Name MO_BS_CA: #REF!
Name MO_BS_Cash: #REF!
Name MO_BS_CL: #REF!
Name MO_BS_CommonStock: #REF!

Sheet Cover
B2: HEICO CORPORATION (HEI)
B4: Legend
B5: Formula
B6: Hardcode
B7: Hardcoded (Own Assumptions)
B8: Formula (Own Assumptions)
B9: Link from another sheet
B12: Model Output - Expectation
B14: Target Price - $ per share | G14: ='FCF & Valuation'!H40
B15: Current Price, 15 March 2024 - $ per share | G15: ='FCF & Valuation'!H41
B16: Potential upside | G16: =(G14-G15)/G15
B17: Call based on DCF Expectation | G17: =IF(G16>0, "BUY", "SELL")

Sheet Drivers>>

Sheet FCF & Valuation
B2: Free Cash Flow Schedule
B3: in $millions, unless otherwise specified
B5: Fiscal year ending December 31, | C5: =2015 | D5: =C5+1 | E5: =D5+1 | F5: =E5+1 | G5: =F5+1 | H5: =G5+3 | I5: =H5+1 | J5: =I5+1 | K5: =J5+1 | L5: =K5+1 | M5: =L5+1 | N5: =M5+1 | O5: =N5+1
B6: EBIT | H6: ='Costs & Expenses Build'!C15-'Costs & Expenses Build'!C23-'Costs & Expenses Build'!C49 | I6: ='Costs & Expenses Build'!D15-'Costs & Expenses Build'!D23-'Costs & Expenses Build'!D49 | J6: ='Costs & Expenses Build'!E15-'Costs & Expenses Build'!E23-'Costs & Expenses Build'!E49 | K6: ='Costs & Expenses Build'!F15-'Costs & Expenses Build'!F23-'Costs & Expenses Build'!F49 | L6: ='Costs & Expenses Build'!G15-'Costs & Expenses Build'!G23-'Costs & Expenses Build'!G49 | M6: ='Costs & Expenses Build'!H15-'Costs & Expenses Build'!H23-'Costs & Expenses Build'!H49 | N6: ='Costs & Expenses Build'!I15-'Costs & Expenses Build'!I23-'Costs & Expenses Build'!I49 | O6: ='Costs & Expenses Build'!J15-'Costs & Expenses Build'!J23-'Costs & Expenses Build'!J49
B7: ( - ) Tax | H7: =H6*20% | I7: =I6*20% | J7: =J6*20% | K7: =K6*20% | L7: =L6*20% | M7: =M6*20% | N7: =N6*20% | O7: =O6*20%
B8: NOPAT | H8: =H6-H7 | I8: =I6-I7 | J8: =J6-J7 | K8: =K6-K7 | L8: =L6-L7 | M8: =M6-M7 | N8: =N6-N7 | O8: =O6-O7
B9: ( + ) D&A | H9: ='Costs & Expenses Build'!C73 | I9: ='Costs & Expenses Build'!D73 | J9: ='Costs & Expenses Build'!E73 | K9: ='Costs & Expenses Build'!F73 | L9: ='Costs & Expenses Build'!G73 | M9: ='Costs & Expenses Build'!H73 | N9: ='Costs & Expenses Build'!I73 | O9: ='Costs & Expenses Build'!J73
B10: ( - ) Changes in NWC | I10: ='Costs & Expenses Build'!D57-'Costs & Expenses Build'!C57 | J10: ='Costs & Expenses Build'!E57-'Costs & Expenses Build'!D57 | K10: =('Costs & Expenses Build'!F57-'Costs & Expenses Build'!E57) | L10: =('Costs & Expenses Build'!G57-'Costs & Expenses Build'!F57) | M10: =('Costs & Expenses Build'!H57-'Costs & Expenses Build'!G57) | N10: =('Costs & Expenses Build'!I57-'Costs & Expenses Build'!H57) | O10: =('Costs & Expenses Build'!J57-'Costs & Expenses Build'!I57)
B11: ( - ) CapEx | H11: ='Costs & Expenses Build'!C66 | I11: ='Costs & Expenses Build'!D66 | J11: ='Costs & Expenses Build'!E66 | K11: ='Costs & Expenses Build'!F66 | L11: ='Costs & Expenses Build'!G66 | M11: ='Costs & Expenses Build'!H66 | N11: ='Costs & Expenses Build'!I66 | O11: ='Costs & Expenses Build'!J66
B12: UFCF | C12: =C8+C9-C10-C11 | D12: =D8+D9-D10-D11 | E12: =E8+E9-E10-E11 | F12: =F8+F9-F10-F11 | G12: =G8+G9-G10-G11 | H12: =H8+H9-H10-H11 | I12: =I8+I9-I10-I11 | J12: =J8+J9-J10-J11 | ... O12: =O8+O9-O10-O11
B13: Discount Factor | K13: =1/(1+H27)^1 | L13: =1/(1+H27)^2 | M13: =1/(1+H27)^3 | N13: =1/(1+H27)^4 | O13: =1/(1+H27)^5
B14: PV of UFCF | K14: =K12*K13 | L14: =L12*L13 | M14: =M12*M13 | N14: =N12*N13 | O14: =O12*O13
B15: Sum PV of UFCF | H15: =SUM(K14:O14)
B18: WACC
B19: Risk Free Rate | H19: ='WACC Build'!C5
B20: Market Risk Premium | H20: 0.0433
B21: 180D Beta | H21: 1.06
B22: Market Cap | H22: 30291.5
B23: Debt Outstanding | H23: 2353.6
B24: Cost of Debt | H24: ='WACC Build'!C7
B25: Cost of Equity | H25: =H19+H21*(H20-H19)
B26: Tax Rate | H26: 0.21
B27: WACC | H27: =(H23/(H23+H22))*H24*(1-H26)+(H22/(H23+H22))*H25
B29: Valuation
B30: Terminal Growth Rate | H30: 0.02
B31: Discount Rate | H31: =H27
B32: Sum of PV of UFCF | H32: =H15
B33: TV | H33: =O12*(1+H30)/(H31-H30)
B34: PV of TV | H34: =H33/(1+H27)^5
B35: EV | H35: =H34+H15
B36: Cash | H36: ='Balance Sheet'!K20
B37: Debt | H37: ='Balance Sheet'!K66+'Balance Sheet'!K78
B38: EqV | H38: =H35+H36-H37
B39: Diluted Shares Outstanding | H39: 138.95
B40: Implied Share Price | H40: =H38/H39
B41: Current Share Price | H41: 242
B42: Implied Upside | H42: =(H40-H41)/H41

Sheet Revenue Build
A2: x | B2: Revenue Build
B3: in $millions, unless otherwise specified
B5: Fiscal year ending December 31, | C5: =2015 | D5: =C5+1 | E5: =D5+1 | F5: =E5+1 | G5: =F5+1 | H5: =G5+3 | I5: =H5+1 | J5: =I5+1 | K5: =J5+1 | L5: =K5+1 | M5: =L5+1 | N5: =M5+1 | O5: =N5+1
B6: Flight Support Group | C6: 140.936 | D6: 173.54 | E6: 236.283 | F6: 291.072 | G6: 337.375
B7: After Market Business | H7: ='Income Statement + Forecast'!C24 | I7: ='Income Statement + Forecast'!D24 | J7: ='Income Statement + Forecast'!E24 | K7: ='Income Statement + Forecast'!F24 | L7: ='Income Statement + Forecast'!G24 | M7: ='Income Statement + Forecast'!H24 | N7: ='Income Statement + Forecast'!I24 | O7: ='Income Statement + Forecast'!J24
B8: % of Growth | H8: ='Income Statement + Forecast'!C25 | I8: ='Income Statement + Forecast'!D25 | J8: ='Income Statement + Forecast'!E25 | K8: ='Income Statement + Forecast'!F25 | L8: ='Income Statement + Forecast'!G25 | M8: ='Income Statement + Forecast'!H25 | N8: ='Income Statement + Forecast'!I25 | O8: ='Income Statement + Forecast'!J25
B9: Repair and Overhaul Parts and Services | H9: ='Income Statement + Forecast'!C29 | I9: ='Income Statement + Forecast'!D29 | J9: ='Income Statement + Forecast'!E29 | K9: ='Income Statement + Forecast'!F29 | L9: ='Income Statement + Forecast'!G29 | M9: ='Income Statement + Forecast'!H29 | N9: ='Income Statement + Forecast'!I29 | O9: ='Income Statement + Forecast'!J29
B10: % of Growth | H10: ='Income Statement + Forecast'!C30 | I10: ='Income Statement + Forecast'!D30 | J10: ='Income Statement + Forecast'!E30 | K10: ='Income Statement + Forecast'!F30 | L10: ='Income Statement + Forecast'!G30 | M10: ='Income Statement + Forecast'!H30 | N10: ='Income Statement + Forecast'!I30 | O10: ='Income Statement + Forecast'!J30
B11: Specialty Products | H11: ='Income Statement + Forecast'!C34 | I11: ='Income Statement + Forecast'!D34 | J11: ='Income Statement + Forecast'!E34 | K11: ='Income Statement + Forecast'!F34 | L11: ='Income Statement + Forecast'!G34 | M11: ='Income Statement + Forecast'!H34 | N11: ='Income Statement + Forecast'!I34 | O11: ='Income Statement + Forecast'!J34
B12: % of Growth | H12: ='Income Statement + Forecast'!C35 | I12: ='Income Statement + Forecast'!D35 | J12: ='Income Statement + Forecast'!E35 | K12: ='Income Statement + Forecast'!F35 | L12: ='Income Statement + Forecast'!G35 | M12: ='Income Statement + Forecast'!H35 | N12: ='Income Statement + Forecast'!I35 | O12: ='Income Statement + Forecast'!J35
B13: Total Flight Support Group Revenue | H13: ='Income Statement + Forecast'!C39 | I13: ='Income Statement + Forecast'!D39 | J13: ='Income Statement + Forecast'!E39 | K13: ='Income Statement + Forecast'!F39 | L13: ='Income Statement + Forecast'!G39 | M13: ='Income Statement + Forecast'!H39 | N13: ='Income Statement + Forecast'!I39 | O13: ='Income Statement + Forecast'!J39
B14: Electronic Technology Group | C14: 140.936 | D14: 173.54 | E14: 236.283 | F14: 291.072 | G14: 337.375
B15: Defense, Space, Aerospace | H15: ='Income Statement + Forecast'!C11 | I15: ='Income Statement + Forecast'!D11 | J15: ='Income Statement + Forecast'!E11 | K15: ='Income Statement + Forecast'!F11 | L15: ='Income Statement + Forecast'!G11 | M15: ='Income Statement + Forecast'!H11 | N15: ='Income Statement + Forecast'!I11 | O15: ='Income Statement + Forecast'!J11
B16: % of Growth | H16: ='Income Statement + Forecast'!C12 | I16: ='Income Statement + Forecast'!D12 | J16: ='Income Statement + Forecast'!E12 | K16: ='Income Statement + Forecast'!F12 | L16: ='Income Statement + Forecast'!G12 | M16: ='Income Statement + Forecast'!H12 | N16: ='Income Statement + Forecast'!I12 | O16: ='Income Statement + Forecast'!J12
B17: Other Industries | H17: ='Income Statement + Forecast'!C16 | I17: ='Income Statement + Forecast'!D16 | J17: ='Income Statement + Forecast'!E16 | K17: ='Income Statement + Forecast'!F16 | L17: ='Income Statement + Forecast'!G16 | M17: ='Income Statement + Forecast'!H16 | N17: ='Income Statement + Forecast'!I16 | O17: ='Income Statement + Forecast'!J16
B18: % of Growth | H18: ='Income Statement + Forecast'!C17 | I18: ='Income Statement + Forecast'!D17 | J18: ='Income Statement + Forecast'!E17 | K18: ='Income Statement + Forecast'!F17 | L18: ='Income Statement + Forecast'!G17 | M18: ='Income Statement + Forecast'!H17 | N18: ='Income Statement + Forecast'!I17 | O18: ='Income Statement + Forecast'!J17
B19: Total Electronic Technology Group Revenue | H19: =SUM(H15+H17) | I19: =SUM(I15+I17) | J19: =SUM(J15+J17) | K19: =SUM(K15+K17) | L19: =SUM(L15+L17) | M19: =SUM(M15+M17) | N19: =SUM(N15+N17) | O19: =SUM(O15+O17)
A20: x | B20: Total Revenue | C20: =SUM(C6:C19) | D20: =SUM(D6:D19) | E20: =SUM(E6:E19) | F20: =SUM(F6:F19) | G20: =SUM(G6:G19) | H20: =H13+H19 | I20: =I13+I19 | J20: =J13+J19 | K20: =K13+K19 | L20: =L13+L19 | M20: =M13+M19 | N20: =N13+N19 | O20: =O13+O19
B21: Product Cost of Good Sold | H21: ='Income Statement + Forecast'!C42 | I21: ='Income Statement + Forecast'!D42 | J21: ='Income Statement + Forecast'!E42 | K21: ='Costs & Expenses Build'!F23 | L21: ='Costs & Expenses Build'!G23 | M21: ='Costs & Expenses Build'!H23 | N21: ='Costs & Expenses Build'!I23 | O21: ='Costs & Expenses Build'!J23
B22: % of Growth | H22: =H21/H20 | I22: =I21/I20 | J22: =J21/J20 | K22: ='Costs & Expenses Build'!F26 | L22: ='Costs & Expenses Build'!G26 | M22: ='Costs & Expenses Build'!H26 | N22: ='Costs & Expenses Build'!I26 | O22: ='Costs & Expenses Build'!J26
A23: x | B23: Total Cost of Revenue | C23: =SUM(#REF!) | D23: =SUM(#REF!) | E23: =SUM(#REF!) | F23: =SUM(#REF!) | G23: =SUM(#REF!) | H23: 1345.6 | I23: 1814.6 | J23: 2355.9 | K23: 2742.06 | L23: 3281.83 | M23: 3890.32 | N23: 4658.81 | O23: 5643.77
B24: R&D Expenses | C24: 32.24 | D24: 38.98 | E24: 43.49 | F24: 55.902 | G24: 61.815 | H24: 76.061 | I24: 95.773 | J24: 111.265 | K24: =K25*K20 | L24: =L25*L20 | M24: =M25*M20 | N24: =N25*N20 | O24: =O25*O20
B25: % of Expenses | H25: 0.03 | I25: 0.03 | J25: 0.03 | K25: 0.032 | L25: 0.031 | M25: 0.03 | N25: 0.031 | O25: 0.031
B26: Stock-based Compensation | C26: 40.002 | D26: 44.272 | E26: 72.755 | F26: 89.204 | G26: 114.443 | H26: ='Costs & Expenses Build'!C37 | I26: ='Costs & Expenses Build'!D37 | J26: ='Costs & Expenses Build'!E37 | K26: ='Costs & Expenses Build'!F37 | L26: ='Costs & Expenses Build'!G37 | M26: ='Costs & Expenses Build'!H37 | N26: ='Costs & Expenses Build'!I37 | O26: ='Costs & Expenses Build'!J37
B27: % of Expenses | H27: ='Costs & Expenses Build'!C38 | I27: ='Costs & Expenses Build'!D38 | J27: ='Costs & Expenses Build'!E38 | K27: ='Costs & Expenses Build'!F38 | L27: ='Costs & Expenses Build'!G38 | M27: ='Costs & Expenses Build'!H38 | N27: ='Costs & Expenses Build'!I38 | O27: ='Costs & Expenses Build'!J38
B28: SG&A Expenses | C28: 5.808 | D28: 6.49 | E28: 17.734 | F28: 21.721 | G28: 22.134 | H28: ='Costs & Expenses Build'!C43 | I28: ='Costs & Expenses Build'!D43 | J28: ='Costs & Expenses Build'!E43 | K28: ='Costs & Expenses Build'!F43 | L28: ='Costs & Expenses Build'!G43 | M28: ='Costs & Expenses Build'!H43 | N28: ='Costs & Expenses Build'!I43 | O28: ='Costs & Expenses Build'!J43
B29: % of Expenses | H29: ='Costs & Expenses Build'!C44 | I29: ='Costs & Expenses Build'!D44 | J29: ='Costs & Expenses Build'!E44 | K29: ='Costs & Expenses Build'!F44 | L29: ='Costs & Expenses Build'!G44 | M29: ='Costs & Expenses Build'!H44 | N29: ='Costs & Expenses Build'!I44 | O29: ='Costs & Expenses Build'!J44
A30: x | B30: Total Operating Expenses | C30: =SUM(#REF!) | D30: =SUM(#REF!) | E30: =SUM(#REF!) | F30: =SUM(#REF!) | G30: =SUM(#REF!) | H30: =SUM(H24,H26,H28) | I30: =SUM(I24,I26,I28) | J30: =SUM(J24,J26,J28) | K30: =SUM(K24,K26,K28) | L30: =SUM(L24,L26,L28) | M30: =SUM(M24,M26,M28) | N30: =SUM(N24,N26,N28) | O30: =SUM(O24,O26,O28)
A31: x | B31: Operating income | C31: =C20-C23-#REF! | D31: =D20-D23-#REF! | E31: =E20-E23-#REF! | F31: =F20-F23-#REF! | G31: =G20-G23-#REF! | H31: =(H20-H23)-H30 | I31: =(I20-I23)-I30 | J31: =(J20-J23)-J30 | K31: =(K20-K23)-K30 | L31: =(L20-L23)-L30 | M31: =(M20-M23)-M30 | N31: =(N20-N23)-N30 | O31: =(O20-O23)-O30

Sheet Costs & Expenses Build
A2: x | B2: Costs & Expenses Build
B3: in $millions, unless otherwise specified
B5: Case Selector | C5: 2
B7: Fiscal year ending December 31, | C7: 2022 | D7: =C7+1 | E7: =D7+1 | F7: =E7+1 | G7: =F7+1 | H7: =G7+1 | I7: =H7+1 | J7: =I7+1
B9: KPIs for Hardware | C9: =
B10: Revenue Build
B11: Total Assem Management Solutions Revenue | C11: ='Income Statement + Forecast'!C21 | D11: ='Income Statement + Forecast'!D21 | E11: ='Income Statement + Forecast'!E21 | F11: ='Income Statement + Forecast'!F21 | G11: ='Income Statement + Forecast'!G21 | H11: ='Income Statement + Forecast'!H21 | I11: ='Income Statement + Forecast'!I21 | J11: ='Income Statement + Forecast'!J21
B12: % Growth | D12: =D11/C11-1 | E12: =E11/D11-1 | F12: =F11/E11-1 | G12: =G11/F11-1 | H12: =H11/G11-1 | I12: =I11/H11-1 | J12: =J11/I11-1
B13: Total TechOps Revenue | C13: ='Income Statement + Forecast'!C39 | D13: ='Income Statement + Forecast'!D39 | E13: ='Income Statement + Forecast'!E39 | F13: ='Income Statement + Forecast'!F39 | G13: ='Income Statement + Forecast'!G39 | H13: ='Income Statement + Forecast'!H39 | I13: ='Income Statement + Forecast'!I39 | J13: ='Income Statement + Forecast'!J39
B14: % Growth | D14: =D13/C13-1 | E14: =E13/D13-1 | F14: =F13/E13-1 | G14: =G13/F13-1 | H14: =H13/G13-1 | I14: =I13/H13-1 | J14: =J13/I13-1
B15: Total Revenue | C15: =SUM(C13,C11) | D15: =SUM(D13,D11) | E15: =SUM(E13,E11) | F15: =SUM(F13,F11) | G15: =SUM(G13,G11) | H15: =SUM(H13,H11) | I15: =SUM(I13,I11) | J15: =SUM(J13,J11)
B16: % Growth | D16: =D15/C15-1 | E16: =E15/D15-1 | F16: =F15/E15-1 | G16: =G15/F15-1 | H16: =H15/G15-1 | I16: =I15/H15-1 | J16: =J15/I15-1
B18: ASM as % of Revenue | C18: =C11/C15 | D18: =D11/D15 | E18: =E11/E15 | F18: =F11/F15 | G18: =G11/G15 | H18: =H11/H15 | I18: =I11/I15 | J18: =J11/J15
B19: TechOps as % of Revenue | C19: =C13/C15 | D19: =D13/D15 | E19: =E13/E15 | F19: =F13/F15 | G19: =G13/G15 | H19: =H13/H15 | I19: =I13/I15 | J19: =J13/J15
B21: (COGS as % of Segment Revenue)
B22: Cost of Goods Sold
B23: Product COGS, $mm | C23: ='Income Statement + Forecast'!C42 | D23: ='Income Statement + Forecast'!D42 | E23: ='Income Statement + Forecast'!E42 | F23: =F15*F24 | G23: =G15*G24 | H23: =H15*H24 | I23: =I15*I24 | J23: =J15*J24
B24: % Revenue | C24: =C23/C15 | D24: =D23/D15 | E24: =E23/E15 | F24: =CHOOSE($C$5,F25,F26,F27) | G24: =CHOOSE($C$5,G25,G26,G27) | H24: =CHOOSE($C$5,H25,H26,H27) | I24: =CHOOSE($C$5,I25,I26,I27) | J24: =CHOOSE($C$5,J25,J26,J27)
B25: Bear | F25: =F26+0.01 | G25: =G26+0.01 | H25: =H26+0.01 | I25: =I26+0.01 | J25: =J26+0.01
B26: Base | F26: =60%-3% | G26: =F26+0.01 | H26: =G26+0.01 | I26: =H26+0.01 | J26: =I26+0.01
B27: Bull | F27: =F26-0.01 | G27: =G26-0.01 | H27: =H26-0.01 | I27: =I26-0.01 | J27: =J26-0.01
B29: (OpEx, D&A, CapEx as % of Revenue)
B30: Operating Expenses
B31: R&D Expenses | C31: ='Income Statement + Forecast'!C46 | D31: ='Income Statement + Forecast'!D46 | E31: ='Income Statement + Forecast'!E46 | F31: =F15*F32 | G31: =G15*G32 | H31: =H15*H32 | I31: =I15*I32 | J31: =J15*J32
B32: % Revenue | C32: =C31/C$15 | D32: =D31/D$15 | E32: =E31/E$15 | F32: =CHOOSE($C$5,F33,F34,F35) | G32: =CHOOSE($C$5,G33,G34,G35) | H32: =CHOOSE($C$5,H33,H34,H35) | I32: =CHOOSE($C$5,I33,I34,I35) | J32: =CHOOSE($C$5,J33,J34,J35)
B33: Bear | F33: =F34+0.004 | G33: =G34+0.004 | H33: =H34+0.004 | I33: =I34+0.004 | J33: =J34+0.004
B34: Base | F34: =AVERAGE(C32:E32) | G34: =AVERAGE(F34,E32,D32) | H34: =AVERAGE(G34,F34,E32) | I34: =AVERAGE(F34:H34) | J34: =AVERAGE(G34:I34)
B35: Bull | F35: =F34-0.004 | G35: =G34-0.004 | H35: =H34-0.004 | I35: =I34-0.004 | J35: =J34-0.004
B37: Stock-based Compensation | C37: ='Income Statement + Forecast'!C47 | D37: ='Income Statement + Forecast'!D47 | E37: ='Income Statement + Forecast'!E47 | F37: =F$15*F38 | G37: =G$15*G38 | H37: =H$15*H38 | I37: =I$15*I38 | J37: =J$15*J38
B38: % Revenue | C38: =C37/C$15 | D38: =D37/D$15 | E38: =E37/E$15 | F38: =CHOOSE($C$5,F39,F40,F41) | G38: =CHOOSE($C$5,G39,G40,G41) | H38: =CHOOSE($C$5,H39,H40,H41) | I38: =CHOOSE($C$5,I39,I40,I41) | J38: =CHOOSE($C$5,J39,J40,J41)
B39: Bear | F39: =F40+0.002 | G39: =G40+0.002 | H39: =H40+0.002 | I39: =I40+0.002 | J39: =J40+0.002
B40: Base | F40: =AVERAGE(C38:E38) | G40: =F40+0.006 | H40: =G40+0.006 | I40: =H40+0.006 | J40: =I40+0.006
B41: Bull | F41: =F40-0.002 | G41: =G40-0.002 | H41: =H40-0.002 | I41: =I40-0.002 | J41: =J40-0.002
B43: SG&A Expenses | C43: ='Income Statement + Forecast'!C48 | D43: ='Income Statement + Forecast'!D48 | E43: ='Income Statement + Forecast'!E48 | F43: =F$15*F44 | G43: =G$15*G44 | H43: =H$15*H44 | I43: =I$15*I44 | J43: =J$15*J44
B44: % Expenses | C44: =C43/C$15 | D44: =D43/D$15 | E44: =E43/E$15 | F44: =CHOOSE($C$5,F45,F46,F47) | G44: =CHOOSE($C$5,G45,G46,G47) | H44: =CHOOSE($C$5,H45,H46,H47) | I44: =CHOOSE($C$5,I45,I46,I47) | J44: =CHOOSE($C$5,J45,J46,J47)
B45: Bear | F45: =F46+0.01 | G45: =G46+0.01 | H45: =H46+0.01 | I45: =I46+0.01 | J45: =J46+0.01
B46: Base | F46: =AVERAGE(C44:E44) | G46: =AVERAGE(F46,E44,D44) | H46: =AVERAGE(F46:G46,E44) | I46: =AVERAGE(F46:H46) | J46: =AVERAGE(G46:I46)
B47: Bull | F47: =F46-0.01 | G47: =G46-0.01 | H47: =H46-0.01 | I47: =I46-0.01 | J47: =J46-0.01
B49: Total Operating Expenses | C49: =SUM(C43,C37,C31) | D49: =SUM(D43,D37,D31) | E49: =SUM(E43,E37,E31) | F49: =SUM(F43,F37,F31) | G49: =SUM(G43,G37,G31) | H49: =SUM(H43,H37,H31) | I49: =SUM(I43,I37,I31) | J49: =SUM(J43,J37,J31)
B50: % Growth | D50: =D49/C49-1 | E50: =E49/D49-1 | F50: =F49/E49-1 | G50: =G49/F49-1 | H50: =H49/G49-1 | I50: =I49/H49-1 | J50: =J49/I49-1
A52: x | B52: Working Capital Schedule
B54: Fiscal Year Ending December 31, | C54: 2022 | D54: =C54+1 | E54: =D54+1 | F54: =E54+1 | G54: =F54+1 | H54: =G54+1 | I54: =H54+1 | J54: =I54+1
B57: NWC | C57: ='Balance Sheet'!I20+'Balance Sheet'!I27+'Balance Sheet'!I22-'Balance Sheet'!I63-'Balance Sheet'!I66 | D57: ='Balance Sheet'!J20+'Balance Sheet'!J27+'Balance Sheet'!J22-'Balance Sheet'!J63-'Balance Sheet'!J66 | E57: ='Balance Sheet'!K20+'Balance Sheet'!K27+'Balance Sheet'!K22-'Balance Sheet'!K63-'Balance Sheet'!K66 | F57: =F15*F58 | G57: =G15*G58 | H57: =H15*H58 | I57: =I15*I58 | J57: =J15*J58
B58: % Revenue | C58: =C57/C15 | D58: =D57/D15 | E58: =E57/E15 | F58: =CHOOSE($C$5,F59,F60,F61) | G58: =CHOOSE($C$5,G59,G60,G61) | H58: =CHOOSE($C$5,H59,H60,H61) | I58: =CHOOSE($C$5,I59,I60,I61) | J58: =CHOOSE($C$5,J59,J60,J61)
B59: Bear | F59: =F60-0.8% | G59: =G60-0.8% | H59: =H60-0.8% | I59: =I60-0.8% | J59: =J60-0.8%
B60: Base | F60: =AVERAGE(C58:E58)-5% | G60: =AVERAGE(F60,E58,D58)-8% | H60: =AVERAGE(G60,F60,E58)-7% | I60: =AVERAGE(F60:H60)-7% | J60: =AVERAGE(G60:I60)-7%
B61: Bull | F61: =F60+0.8% | G61: =G60+0.8% | H61: =H60+0.8% | I61: =I60+0.8% | J61: =J60+0.8%
B63: CapEx Schedule
B65: Fiscal Year Ending December 31,
B66: CapEx | C66: ='Cash Flow Statement'!F39 | D66: ='Cash Flow Statement'!G39 | E66: ='Cash Flow Statement'!H39 | F66: =F15*F67 | G66: =G15*G67 | H66: =H15*H67 | I66: =I15*I67 | J66: =J15*J67
B67: % Revenue | C67: =C66/C15 | D67: =D66/D15 | E67: =E66/E15 | F67: =CHOOSE($C$5,F68,F69,F70) | G67: =CHOOSE($C$5,G68,G69,G70) | H67: =CHOOSE($C$5,H68,H69,H70) | I67: =CHOOSE($C$5,I68,I69,I70) | J67: =CHOOSE($C$5,J68,J69,J70)
B68: Bear | F68: =F69-0.2% | G68: =G69-0.2% | H68: =H69-0.2% | I68: =I69-0.2% | J68: =J69-0.2%
B69: Base | F69: =AVERAGE(D67:E67) | G69: =AVERAGE(F69,E67,D67)-0.1% | H69: =AVERAGE(G69,F69,E67)-0.2% | I69: =AVERAGE(F69:H69)-0.3% | J69: =AVERAGE(G69:I69)-0.3%
B70: Bull | F70: =F69+0.2% | G70: =G69+0.2% | H70: =H69+0.2% | I70: =I69+0.2% | J70: =J69+0.2%
B72: D&A
B73: Total D&A | C73: ='Income Statement + Forecast'!D54 | D73: ='Income Statement + Forecast'!E54 | E73: ='Income Statement + Forecast'!F54 | F73: =F79*F74 | G73: =G79*G74 | H73: =H79*H74 | I73: =I79*I74 | J73: =J79*J74
B74: % PP&E | C74: =C73/C79 | D74: =D73/D79 | E74: =E73/E79 | F74: =CHOOSE($C$5,F75,F76,F77) | G74: =CHOOSE($C$5,G75,G76,G77) | H74: =CHOOSE($C$5,H75,H76,H77) | I74: =CHOOSE($C$5,I75,I76,I77) | J74: =CHOOSE($C$5,J75,J76,J77)
B75: Bear | F75: =F76 | G75: =G76 | H75: =H76 | I75: =I76 | J75: =J76
B76: Base | F76: =AVERAGE(C74:E74) | G76: =AVERAGE(F76,E74,D74) | H76: =AVERAGE(G76,F76,E74) | I76: =AVERAGE(F76:H76) | J76: =AVERAGE(G76:I76)
B77: Bull | F77: =F76 | G77: =G76 | H77: =H76 | I77: =I76 | J77: =J76
B79: PP&E | C79: ='Balance Sheet'!I37 | D79: ='Balance Sheet'!J37 | E79: ='Balance Sheet'!K37 | F79: =E79+F66 | G79: =F81+G66 | H79: =G81+H66 | I79: =H81+I66 | J79: =I81+J66
B80: LEss: Depreciation | C80: ='Balance Sheet'!I37 | F80: =F73 | G80: =G73 | H80: =H73 | I80: =I73 | J80: =J73
B81: EB: PP&E | F81: =F79-F80 | G81: =G79-G80 | H81: =H79-H80 | I81: =I79-I80 | J81: =J79-J80

Sheet WACC Build
B2: Cost of debt computation
B4: Latest risk-free rate
B5: US 10Y Treasury Yield | C5: 0.04255
B6: Spread | C6: =G32
B7: Cost of debt | C7: =C5+C6
B9: HEI Credit Rating
B10: Moody's | C10: Baa2
B11: Fitch | C11: BBB
B13: Comps Credit Spreads
C15: Credit Rating | D15: Agency
B16: TransDigm Group | C16: B | D16: Moody's
B17: AAR Corp | C17: Ba2 | D17: Moody's
B18: FTAI Aviation Ltd. | C18: Ba2 | D18: Moody's
B19: RBC Bearings | C19: BB | D19: S&P
B20: Howmet Aerospace | C20: BBB | D20: S&P
B21: RTX Corporation | C21: Baa1 | D21: Moody's
B22: Moog Inc | C22: BB+ | D22: S&P
B23: Honeywell International | C23: A2 | D23: Moody's
B25: Howmet Bonds | C25: Yield | D25: Maturity | E25: Years | F25: Risk-Free | G25: Spread
B26: 5.900% 2/1/2027 | C26: 0.04502 | D26: 2027 | E26: =D26-2025 | F26: 0.0374 | G26: =C26-F26
B27: 6.750% 1/15/2028 | C27: =4.786% | D27: 2028 | E27: =D27-2025 | F27: 0.0376 | G27: =C27-F27
B28: 3.000% 1/15/2029 | C28: 0.046243 | D28: 2029 | E28: =D28-2025 | F28: 0.0382 | G28: =C28-F28
B29: 4.850% 10/15/2031 | C29: 0.048548 | D29: 2031 | E29: =D29-2025 | F29: 0.0395 | G29: =C29-F29
B30: 5.950% 2/1/2037 | C30: 0.055012 | D30: 2037 | E30: =D30-2025 | F30: 0.044 | G30: =C30-F30
F32: AVG | G32: =AVERAGE(G26:G30)

Sheet Comps
A1: NYSE: HEI
A2: Share Price (As of 04/24/2025) | B2: $242.04
A3: Diluted Shares Outstanding | B3: 138.95M
A4: Market Cap | B4: $29.72B
A5: Company P/E | B5: 66.8x
A6: Industry P/E | B6: 45.85x
A7: EV/EBITDA | B7: 31.78x
A8: Industry EV/EBITDA | B8: 23.04x
A11: Comparables Analysis (Aircraft Aftermarket)
A12: Stock prices and multiples as of 04/23/2025, Monetary Figures in $millions, except for stock price, multiples and market cap
A13: Company | B13: Country | C13: Ticker | D13: Market Valuation | G13: Financial Performance (NTM) | J13: Multiples
D14: Price | E14: Market Cap | F14: TEV | G14: Sales | H14: EBITDA | I14: Net Income | J14: EV/EBITDA | K14: EV/Sales | L14: P/E
A15: HEICO Corp | B15: USA | C15: HEI | D15: 246.35 | E15: $ 29.72B | F15: 32009.45 | G15: 4298 | H15: 1145 | I15: 627.84 | J15: 31.78 | K15: 8.3 | L15: 60.03
A16: TransDigm Group | B16: USA | C16: TDG | D16: 1362.31 | E16: $ 75.83B | F16: 94472.04 | G16: 8880 | H16: 4710 | I16: 2175 | J16: 23.86 | K16: 11.9 | L16: 48.22
A17: AAR Corp | B17: USA | C17: AIR | D17: 47 | E17: $ 1.90B | F17: 3414.57 | G17: 787.94 | H17: 140.26 | I17: 59.03 | J17: 15.7 | K17: 1.47 | L17: 40.81
A18: FTAI Aviation Ltd. | B18: USA | C18: FTAI | D18: 101.85 | E18: $ 9.83B | F18: 18096.92 | G18: 2503 | H18: 1108 | I18: 590.51 | J18: 37.23 | K18: 10.43 | L18: 43.28
A19: RBC Bearings | B19: USA | C19: RBC | D19: 329.7 | E19: $ 10.38B | F19: 9070.13 | G19: 1639 | H19: 514.52 | I19: 289.49 | J19: 19.5 | K19: 5.81 | L19: 45.3
A20: Mean | J20: =AVERAGE(J15:J19) | K20: =AVERAGE(K15:K19) | L20: =AVERAGE(L15:L19)
A21: Median | J21: =MEDIAN(J15:J19) | K21: =MEDIAN(K15:K19) | L21: =MEDIAN(L15:L19)
A25: Comparables Analysis (OEMs)
A26: Stock prices and multiples as of 04/23/2025, Monetary Figures in $millions, except for stock price, multiples and market cap
A27: Company | B27: Country | C27: Ticker | D27: Market Valuation | G27: Financial Performance (NTM) | J27: Multiples
D28: Price | E28: Market Cap | F28: TEV | G28: Sales | H28: EBITDA | I28: Net Income | J28: EV/EBITDA | K28: EV/Sales | L28: P/E
A29: HEICO Corp | B29: USA | C29: HEI | D29: 246.35 | E29: $ 29.72B | F29: 32009.45 | G29: 4298 | H29: 1145 | I29: 627.84 | J29: 31.78 | K29: 8.3 | L29: 60.03
A30: Howmet Aerospace | B30: USA | C30: HWM | D30: 132 | E30: $ 53.99B | F30: 47001.85 | G30: 8072 | H30: 2172 | I30: 1326 | J30: 24.39 | K30: 6.34 | L30: 47.47
A31: FTAI Aviation Ltd. | B31: USA | C31: FTAI | D31: 101.85 | E31: $ 9.83B | F31: 18096.92 | G31: 2503 | H31: 1108 | I31: 590.51 | J31: 37.23 | K31: 10.43 | L31: 43.28
A32: AAR Corp | B32: USA | C32: AIR | D32: 47 | E32: $ 1.90B | F32: 3414.57 | G32: 787.94 | H32: 140.26 | I32: 59.03 | J32: 15.7 | K32: 1.47 | L32: 40.81
A33: RTX Corporation | B33: USA | C33: RTX | D33: 121.05 | E33: $ 162.95B | F33: 191638.25 | G33: 84224 | H33: 13732 | I33: 8131 | J33: 13.61 | K33: 2.37 | L33: 35.76
A34: Moog Inc | B34: USA | C34: MOGa | D34: 155 | E34: $ 5.56B | F34: 7613.94 | G34: 3703 | H34: 546.5 | I34: 330.98 | J34: 16.27 | K34: 2.11 | L34: 25.74
A35: Honeywell International | B35: USA | C35: HON.O | D35: 199.24 | E35: $ 129.13B | F35: 167572.38 | G35: 40268 | H35: 10338 | I35: 6640 | J35: 17.81 | K35: 4.35 | L35: 23.06
A36: Mean | J36: =AVERAGE(J29:J35) | K36: =AVERAGE(K29:K35) | L36: =AVERAGE(L29:L35)
A37: Median | J37: =MEDIAN(J29:J35) | K37: =MEDIAN(K29:K35) | L37: =MEDIAN(L29:L35)
A39: Comparables Analysis (High-tech Electronics / Military Components)
A40: Stock prices and multiples as of 04/23/2025, Monetary Figures in $millions, except for stock price, multiples and market cap
A41: Company | B41: Country | C41: Ticker | D41: Market Valuation | G41: Financial Performance (NTM) | J41: Multiples
D42: Price | E42: Market Cap | F42: TEV | G42: Sales | H42: EBITDA | I42: Net Income | J42: EV/EBITDA | K42: EV/Sales | L42: P/E
A43: Mercury Systems Inc | B43: USA | C43: MRCY | D43: 48.31 | E43: $ 2.97B | F43: 2012.73 | G43: 881.99 | H43: 103.1 | I43: 23.33 | J43: 31.19 | K43: 3.67 | L43: 68.79
A44: HEICO Corp | B44: USA | C44: HEI | D44: 246.35 | E44: $ 29.72B | F44: 32009.45 | G44: 4298 | H44: 1145 | I44: 627.84 | J44: 31.78 | K44: 8.3 | L44: 60.03
A45: TransDigm Group | B45: USA | C45: TDG | D45: 1362.31 | E45: $ 75.83B | F45: 94472.04 | G45: 8880 | H45: 4710 | I45: 2175 | J45: 23.86 | K45: 11.9 | L45: 48.22
A46: Curtiss-Wright Corp | B46: USA | C46: CW | D46: 325 | E46: $ 12.65B | F46: 14137.32 | G46: 3361 | H46: 721.87 | I46: 462.96 | J46: 21.67 | K46: 4.53 | L46: 31.79
A47: RTX Corporation | B47: USA | C47: RTX | D47: 121.05 | E47: $ 162.95B | F47: 191638.25 | G47: 84224 | H47: 13732 | I47: 8131 | J47: 13.61 | K47: 2.37 | L47: 35.76
A48: Mean | J48: =AVERAGE(J43:J47) | K48: =AVERAGE(K43:K47) | L48: =MEDIAN(L43:L47)
A49: Median | J49: =MEDIAN(J43:J47) | K49: =MEDIAN(K43:K47) | L49: =AVERAGE(L43:L47)

Sheet Financial Statements >>

Sheet Income Statement + Forecast
A1: HEI | Statement App | Income Statement | C1: 25-Apr-2025
A3: Consolidated | USD
A5: Next Earning Report | C5: 26-May-2025
E7: HISTORICAL (ACTUALS) | F7: FORECAST (MEAN)
B8: FY Oct-21 | C8: FY Oct-22 | D8: FY Oct-23 | E8: FY Oct-24 | F8: FY Oct-25 | G8: FY Oct-26 | H8: FY Oct-27 | I8: 2028 | J8: 2029
A9: REVENUE | B9: 1865.682 | C9: 2208.322 | D9: 2968.105 | E9: 3857.669 | F9: 4297.7082 | G9: 4610.7225 | H9: 4921.9458
A10: ELECTRONIC TECHNOLOGIES GROUP
A11: Defense, Space, Aerospace | B11: 709.621 | C11: 672.147 | D11: 918.374 | E11: 1004.511 | F11: =E11*(1+F12) | G11: =F11*(1+G12) | H11: =G11*(1+H12) | I11: =H11*(1+I12) | J11: =I11*(1+J12)
A12: Growth % | C12: =C11/B11-1 | D12: =(D11-C11)/C11 | E12: =(E11-D11)/D11 | F12: =CHOOSE('Costs & Expenses Build'!$C$5,F13,F14,F15) | G12: =CHOOSE('Costs & Expenses Build'!$C$5,G13,G14,G15) | H12: =CHOOSE('Costs & Expenses Build'!$C$5,H13,H14,H15) | I12: =CHOOSE('Costs & Expenses Build'!$C$5,I13,I14,I15) | J12: =CHOOSE('Costs & Expenses Build'!$C$5,J13,J14,J15)
A13: Bear | F13: =F14-2% | G13: =G14-2% | H13: =H14-2% | I13: =I14-2% | J13: =J14-2%
A14: Base | F14: =AVERAGE(C12:E12)-3% | G14: =AVERAGE(D12,E12,F14) | H14: =AVERAGE(E12,F14,G14) | I14: =AVERAGE(F14:H14) | J14: =AVERAGE(G14:I14)
A15: Bull | F15: =F14+2% | G15: =G14+2% | H15: =H14+2% | I15: =I14+2% | J15: =J14+2%
A16: Other Industries | B16: 249.582 | C16: 300.328 | D16: 306.848 | E16: 259.115 | F16: =E16*(1+F17) | G16: =F16*(1+G17) | H16: =G16*(1+H17) | I16: =H16*(1+I17) | J16: =I16*(1+J17)
A17: Growth % | C17: =(C16-B16)/B16 | D17: =(D16-C16)/C16 | E17: =(E16-D16)/D16 | F17: =CHOOSE('Costs & Expenses Build'!$C$5,F18,F19,F20) | G17: =CHOOSE('Costs & Expenses Build'!$C$5,G18,G19,G20) | H17: =CHOOSE('Costs & Expenses Build'!$C$5,H18,H19,H20) | I17: =CHOOSE('Costs & Expenses Build'!$C$5,I18,I19,I20) | J17: =CHOOSE('Costs & Expenses Build'!$C$5,J18,J19,J20)
A18: Bear | F18: =F19-0.5% | G18: =G19-0.5% | H18: =H19-0.5% | I18: =I19-0.5% | J18: =J19-0.5%
A19: Base | F19: =AVERAGE(C17:E17) | G19: =AVERAGE(D17,E17,F19) | H19: =AVERAGE(E17,F19,G19) | I19: =AVERAGE(F17,G19,H19) | J19: =AVERAGE(G17,H19,I19)
A20: Bull | F20: =F19+0.5% | G20: =G19+0.5% | H20: =H19+0.5% | I20: =I19+0.5% | J20: =J19+0.5%
A21: Total Sector Sells | C21: 972.475 | D21: 1225.22 | E21: 1263.626 | F21: =F11+F16 | G21: =G11+G16 | H21: =H11+H16 | I21: =I11+I16 | J21: =J11+J16
A23: FLIGHT SUPPORT GROUP | B23: 927.089 | C23: 1255.212 | D23: 1770.185 | E23: 2639.354 | F23: 2973.929 | G23: 3170.0547 | H23: 3381.7
A24: Aftermarket | B24: 535.217 | C24: 694.9 | D24: 1040.502 | E24: 1658.431 | F24: =E24*(1+F25) | G24: =F24*(1+G25) | H24: =G24*(1+H25) | I24: =H24*(1+I25) | J24: =I24*(1+J25)
A25: Growth % | C25: =(C24-B24)/B24 | D25: =(D24-C24)/C24 | E25: =(E24-D24)/D24 | F25: =CHOOSE('Costs & Expenses Build'!$C$5,F26,F27,F28) | G25: =CHOOSE('Costs & Expenses Build'!$C$5,G26,G27,G28) | H25: =CHOOSE('Costs & Expenses Build'!$C$5,H26,H27,H28) | I25: =CHOOSE('Costs & Expenses Build'!$C$5,I26,I27,I28) | J25: =CHOOSE('Costs & Expenses Build'!$C$5,J26,J27,J28)
A26: Bear | F26: =F27-3% | G26: =G27-3% | H26: =H27-3% | I26: =I27-3% | J26: =J27-3%
A27: Base | F27: =E25-40% | G27: =F25-5% | H27: =G25-2% | I27: =H25-2% | J27: =I25-2%
A28: Bull | F28: =F27+3% | G28: =G27+3% | H28: =H27+3% | I28: =I27+3% | J28: =J27+3%
A29: Repair and overhaul parts and services | B29: 208.215 | C29: 264.986 | D29: 366.566 | E29: 593.237 | F29: =E29*(1+F30) | G29: =F29*(1+G30) | H29: =G29*(1+H30) | I29: =H29*(1+I30) | J29: =I29*(1+J30)
A30: Growth % | C30: =(C29-B29)/B29 | D30: =(D29-C29)/C29 | E30: =(E29-D29)/D29 | F30: =CHOOSE('Costs & Expenses Build'!$C$5,F31,F32,F33) | G30: =CHOOSE('Costs & Expenses Build'!$C$5,G31,G32,G33) | H30: =CHOOSE('Costs & Expenses Build'!$C$5,H31,H32,H33) | I30: =CHOOSE('Costs & Expenses Build'!$C$5,I31,I32,I33) | J30: =CHOOSE('Costs & Expenses Build'!$C$5,J31,J32,J33)
A31: Bear | F31: =F32-3% | G31: =G32-3% | H31: =H32-3% | I31: =I32-3% | J31: =J32-3%
A32: Base | F32: =AVERAGE(C30,D30) | G32: =F32+2% | H32: =G32+2% | I32: =H32+2% | J32: =I32+2%
A33: Bull | F33: =F32+3% | G33: =G32+3% | H33: =H32+3% | I33: =I32+3% | J33: =J32+3%
A34: Specialty products | B34: 183.567 | C34: 295.326 | D34: 363.117 | E34: 387.686 | F34: =E34*(1+F35) | G34: =F34*(1+G35) | H34: =G34*(1+H35) | I34: =H34*(1+I35) | J34: =I34*(1+J35)
A35: Growth % | C35: =(C34-B34)/B34 | D35: =(D34-C34)/C34 | E35: =(E34-D34)/D34 | F35: =CHOOSE('Costs & Expenses Build'!$C$5,F36,F37,F38) | G35: =CHOOSE('Costs & Expenses Build'!$C$5,G36,G37,G38) | H35: =CHOOSE('Costs & Expenses Build'!$C$5,H36,H37,H38) | I35: =CHOOSE('Costs & Expenses Build'!$C$5,I36,I37,I38) | J35: =CHOOSE('Costs & Expenses Build'!$C$5,J36,J37,J38)
A36: Bear | F36: =F37-2% | G36: =G37-2% | H36: =H37-2% | I36: =I37-2% | J36: =J37-2%
A37: Base | F37: 0.1 | G37: =F37+2% | H37: =G37+2% | I37: =H37+2% | J37: =I37+2%
A38: Bull | F38: =F37+2% | G38: =G37+2% | H38: =H37+2% | I38: =I37+2% | J38: =J37+2%
A39: Total Sector Sales | B39: 927.089 | C39: 1255.212 | D39: 1770.185 | E39: 2639.354 | F39: =F34+F29+F24 | G39: =G34+G29+G24 | H39: =H34+H29+H24 | I39: =I34+I29+I24 | J39: =J34+J29+J24
A40: Total Sales
A42: COST OF GOODS SOLD | C42: 1345.563 | D42: 1814.617 | E42: 2355.943 | F42: 2573.3891 | G42: 2740.0171 | H42: 2795.7133 | I42: ='Costs & Expenses Build'!I23
A43: GROSS INCOME | C43: =C9-C42 | D43: =D9-D42 | E43: =E9-E42 | F43: =F9-F42 | G43: =G9-G42 | H43: =H9-H42
A44: GROSS PROFIT MARGIN | C44: 0.3907 | D44: 0.3886 | E44: 0.3892 | F44: 0.3958556 | G44: 0.4007875 | H44: 0.4126667
A46: R&D EXPENSE | C46: 76.061 | D46: 95.773 | E46: 111.265 | F46: 71.55 | G46: 74.85 | H46: 78.2
A47: STOCK BASED COMPENSATION | C47: 12.646 | D47: 15.475 | E47: 18.775 | F47: 16.19433 | G47: 16.206 | H47: 21.9
A48: SG&A EXPENSE | C48: 365.915 | D48: 528.149 | E48: 677.271 | F48: 754.60067 | G48: 795.23133 | H48: 853.4
A49: OPERATING EXPENSE | C49: 1711.478 | D49: 2342.766 | E49: 3033.214 | F49: 3335.775 | G49: 3559.7667 | H49: 3674
A51: EBITDA | C51: 593.742 | D51: 758.31 | E51: 1002.23 | F51: 1144.8562 | G51: 1239.5154 | H51: 1337.6599
A52: EBITDA MARGIN | C52: - | D52: - | E52: - | F52: 0.2650909 | G52: 0.2675546 | H52: 0.2706
A53: EBITDA PER SHARE | C53: - | D53: 5.459 | E53: 7.15 | F53: 8.27 | G53: 9.03 | H53: 9.84
A54: DEPRECIATION & AMORTIZATION | C54: 96.333 | D54: 130.043 | E54: 175.331 | F54: 182.3355 | G54: 186.064 | H54: 191.338
A55: DEPRECIATION | C55: 28.717 | D55: 40.278 | E55: 49.128 | F55: 66 | G55: 69 | H55: 73
A56: AMORTIZATION | C56: 66.076 | D56: 89.765 | E56: 126.203 | F56: 64.5 | G56: 69 | H56: 148
A58: EBIT | C58: 496.844 | D58: 625.339 | E58: 824.455 | F58: 955.43956 | G58: 1046.323 | H58: 1145.4956
A59: ELECTRONIC TECHNOLOGIES GROUP | C59: 269.473 | D59: 285.053 | E59: 288.193 | F59: 322.97583 | G59: 351.05033 | H59: 380
A60: FLIGHT SUPPORT GROUP | C60: 267.167 | D60: 387.297 | E60: 593.074 | F60: 690.211 | G60: 746.69683 | H60: 808.13333
A61: INTERSEGMENT SALES | C61: -39.796 | D61: -47.011 | E61: -56.812 | F61: -60.47783 | G61: -60.96667 | H61: -71.96667
A63: EBIT MARGIN | C63: - | D63: - | E63: - | F63: 0.22467 | G63: 0.2268778 | H63: 0.2316
A64: INTEREST EXPENSE | C64: 5.808 | D64: 71.773 | E64: 149.313 | F64: 124.11436 | G64: 108.22727 | H64: 80
A65: OTHER INCOME/EXPENSE | C65: - | D65: - | E65: - | F65: -19.43333 | G65: -19.66667 | H65: 0
A67: PRE-TAX PROFIT | C67: 491.023 | D67: 555.283 | E67: 677.586 | F67: 830.60113 | G67: 939.27367 | H67: 1060.0267
A68: TAX PROVISION | C68: 100.4 | D68: 110.9 | E68: 118.5 | F68: 148.47264 | G68: 181.20337 | H68: 199.825
A69: TAX RATE | C69: 0.2044711 | D69: 0.199718 | E69: 0.1748 | F69: 0.1823 | G69: 0.1972 | H69: 0.196
A71: NET INCOME | C71: 351.675 | D71: 403.596 | E71: 514.109 | F71: 627.84394 | G71: 701.29747 | H71: 792.65178
A72: NET INCOME MARGIN | C72: - | D72: - | E72: - | F72: 0.1499 | G72: 0.1542333 | H72: 0.1620333
A74: EARNINGS PER SHARE | C74: 2.55 | D74: 2.91 | E74: 3.67 | F74: 4.44705 | G74: 4.96844 | H74: 5.64222
A75: EBITDA REPORTED | C75: 593.177 | D75: 755.382 | E75: 999.786 | F75: 1136.6667 | G75: 1238.7167 | H75: 1363.6667
A76: PRE-TAX PROFIT REPORTED | C76: 491.023 | D76: 555.283 | E76: 677.586 | F76: 833.885 | G76: 937.20639 | H76: 1063.9883
A77: NET INCOME REPORTED | C77: 351.675 | D77: 403.596 | E77: 514.109 | F77: 629.43414 | G77: 699.63836 | H77: 794.12714
A78: EARNINGS PER SHARE REPORTED | C78: 2.55 | D78: 2.91 | E78: 3.67 | F78: 4.44625 | G78: 4.95875 | H78: 5.65
A79: DIVIDEND PER SHARE | C79: - | D79: 0.2 | E79: - | F79: 0.24 | G79: 0.266 | H79: 0.30429
A80: NUMBER OF SHARES OUTSTANDING | C80: 138.037 | D80: 138.905 | E80: 140.198 | F80: 140.53146 | G80: 140.93146 | H80: 140.46667

Sheet Cash Flow Statement
A1: Company Fundamentals - Cash Flow
A2: Company Name | B2: HEICO Corp (HEI)
A3: Country of Exchange | B3: United States of America
A4: Country of Headquarters | B4: United States of America
A5: TRBC Industry Group | B5: Aerospace & Defense
A6: CF Template | B6: IND
A7: Consolidation Basis | B7: Consolidated
A8: Scaling | B8: Millions
A9: Period | B9: Annual
A10: Export Date | B10: 45772.964
A11: Statement Data | B11: 2018 | C11: 2019 | D11: 2020 | E11: 2021 | F11: 2022 | G11: 2023 | H11: 2024
A12: Period End Date | B12: 43404 | C12: 43769 | D12: 44135 | E12: 44500 | F12: 44865 | G12: 45230 | H12: 45596
A13: Statement Date | B13: 43403 | C13: 43768 | D13: 44134 | E13: 44499 | F13: 44864 | G13: 45229 | H13: 45595
A14: Standardized Currency | B14: USD | C14: USD | D14: USD | E14: USD | F14: USD | G14: USD | H14: USD
A15: Template Type | B15: Industrial - Indirect | C15: Industrial - Indirect | D15: Industrial - Indirect | E15: Industrial - Indirect | F15: Industrial - Indirect | G15: Industrial - Indirect | H15: Industrial - Indirect
A17: Cash Flow - Standardized (Currency: Standardized)
A18: Field Name | B18: 30-10-2018 | C18: 30-10-2019 | D18: 30-10-2020 | E18: 30-10-2021 | F18: 30-10-2022 | G18: 30-10-2023 | H18: 30-10-2024
A19: Operating Cash Flow - Indirect
A20: Profit/(Loss) - Starting Line - Cash Flow | B20: 285.69 | C20: 359.74 | D20: 335.86 | E20: 329.76 | F20: 390.62 | G20: 444.38 | H20: 559.09
A21: Non-cash Items & Reconciliation Adjustments - Cash Flow | B21: 80.52 | C21: 96.49 | D21: 102.61 | E21: 100.02 | F21: 123.23 | G21: 108.2 | H21: 234.66
A22: Other Non-Cash Items & Reconciliation Adjustments - Cash Flow - to Reconcile | B22: 7.02 | C22: 9.05 | D22: 9.92 | E22: 13.58 | F22: 5.38 | G22: -10.79 | H22: 55.05
A23: Depreciation, Depletion & Amortization including Impairment - Cash Flow - to Reconcile | B23: 77.19 | C23: 83.5 | D23: 88.56 | E23: 93.02 | F23: 96.33 | G23: 130.04 | H23: 182.83
A24: Depreciation & Depletion - Property, Plant & Equipment - Cash Flow - to Reconcile | B24: 77.19 | C24: 83.5 | D24: 88.56 | E24: 93.02 | F24: 96.33 | G24: 130.04 | H24: 175.33
A25: Impairment - Property, Plant & Equipment including Intangible Assets - Cash Flow - to Reconcile | H25: 7.5
A26: Deferred Income Taxes & Income Tax Credits - Cash Flow - to Reconcile | B26: -12.98 | C26: -6.39 | D26: -6 | E26: -15.63 | F26: 8.88 | G26: -26.53 | H26: -22
A27: Share Based Payments - Cash Flow - to Reconcile | B27: 9.28 | C27: 10.33 | D27: 10.13 | E27: 9.06 | F27: 12.65 | G27: 15.48 | H27: 18.77
A28: Cash Flow from Operating Activities before Changes in Working Capital | B28: 366.2 | C28: 456.23 | D28: 438.47 | E28: 429.78 | F28: 513.86 | G28: 552.58 | H28: 793.74
A29: Working Capital - Increase/(Decrease) - Cash Flow | B29: -37.72 | C29: -18.85 | D29: -29.34 | E29: 14.3 | F29: -46 | G29: -103.85 | H29: -121.37
A30: Accounts Receivables - Decrease/(Increase) - Cash Flow | B30: -28.57 | C30: -17.39 | D30: 55.12 | E30: -26.92 | F30: -33.42 | G30: -77.24 | H30: -19.52
A31: Inventories - Decrease/(Increase) - Cash Flow | B31: -49.45 | C31: -30.08 | D31: -28.31 | E31: -10.12 | F31: -89.19 | G31: -124.78 | H31: -132.93
A32: Prepaid Expenses - Decrease/(Increase) - Cash Flow | B32: 0.4 | C32: 0.61 | D32: 2.47 | E32: -4.79 | F32: -10.08 | G32: 5.6 | H32: -23.03
A33: Accounts Payable - Increase/(Decrease) - Cash Flow | B33: 17.4 | C33: -3.85 | D33: -30.33 | E33: 6.91 | F33: 25.57 | G33: 10.98 | H33: -9.82
A34: Accrued Expenses - Increase/(Decrease) - Cash Flow | B34: 22.12 | C34: 17.15 | D34: -37.9 | E34: 33.63 | F34: 34.12 | G34: 72.59 | H34: 22.1
A35: Taxes Payable - Increase/(Decrease) - Cash Flow | B35: -12.53 | C35: 1.3 | D35: -9.59 | E35: 2.82 | F35: 11.6 | G35: -4.5 | H35: 20.22
A36: Other Assets & Liabilities - Increase/(Decrease) - Net - Cash Flow | B36: 12.91 | C36: 13.41 | D36: 19.2 | E36: 12.78 | F36: 15.4 | G36: 13.51 | H36: 21.62
A37: Net Cash Flow from Operating Activities | B37: 328.49 | C37: 437.38 | D37: 409.13 | E37: 444.08 | F37: 467.86 | G37: 448.74 | H37: 672.37
A38: Investing Cash Flow
A39: Capital Expenditures - Net - Cash Flow | B39: 41.87 | C39: 28.94 | D39: 22.94 | E39: 36.18 | G39: 49.43 | H39: 58.26
A40: Property, Plant & Equipment - Purchased/(Sold) - Net - Cash Flow | B40: 41.87 | C40: 28.94 | D40: 22.94 | E40: 36.18 | F40: 31.98 | G40: 49.43 | H40: 58.26
A41: Property, Plant & Equipment - Purchased - Cash Flow | B41: 41.87 | C41: 28.94 | D41: 22.94 | E41: 36.18 | F41: 31.98 | G41: 49.43 | H41: 58.26
A42: Capital Expenditures - Total | B42: 41.87 | C42: 28.94 | D42: 22.94 | E42: 36.18 | F42: 31.98 | G42: 49.43 | H42: 58.26
A43: Acquisition & Disposals of Business - Assets - Sold/(Acquired) - Net - Cash Flow | B43: -59.77 | C43: -240.84 | D43: -163.94 | E43: -136.5 | F43: -347.31 | G43: -2421.79 | H43: -219.29
A44: Acquisition of Business - Cash Flow | B44: 59.78 | C44: 240.84 | D44: 163.94 | E44: 136.5 | F44: 347.31 | G44: 2421.79 | H44: 219.29
A45: Investments excluding Loans - Decrease/(Increase) - Cash Flow | B45: -11.5 | C45: -13.7 | D45: -15.9 | E45: -14 | F45: -15.3 | G45: -18.89 | H45: -19.91
A46: Investment Securities - Unclassified - Sold/(Purchased) - Net - Total - Cash Flow | B46: -11.5 | C46: -13.7 | D46: -15.9 | E46: -14 | F46: -15.3 | G46: -18.89 | H46: -19.91
A47: Other Investing Cash Flow - Decrease/(Increase) | B47: -0.36 | C47: 2.83 | D47: 3.74 | E47: 3.23 | F47: -1.24 | G47: 5.65 | H47: 4.26
A48: Net Cash Flow from Investing Activities | B48: -113.51 | C48: -280.65 | D48: -199.04 | E48: -183.45 | F48: -395.83 | G48: -2484.47 | H48: -293.2
A49: Financing Cash Flow
A50: Dividends Paid - Cash - Total - Cash Flow | B50: 15.36 | C50: 18.69 | D50: 21.55 | E50: 23 | F50: 24.47 | G50: 27.37 | H50: 29.07
A51: Dividends - Common - Cash Paid | B51: 15.36 | C51: 18.69 | D51: 21.55 | E51: 23 | F51: 24.47 | G51: 27.37 | H51: 29.07
A52: Stock - Total - Issuance/(Retirement) - Net - Cash Flow | B52: -20.95 | C52: -55.47 | D52: -5.16 | E52: 1.55 | F52: -23.59 | G52: -8.13 | H52: -21.96
A53: Options Exercised - Cash Flow | B53: -20.95 | C53: -55.47 | D53: -5.16 | E53: 1.55 | F53: -23.59 | G53: -8.13 | H53: -21.96
A54: Minority Interests & Joint Ventures - Net - Cash Flow | D54: 6.85 | E54: -1.8 | F54: -8.73 | G54: -2.73 | H54: -26.57
A55: Debt - Long-Term & Short-Term - Issuance/(Retirement) - Total - Cash Flow | B55: -148 | C55: 30 | D55: 177 | E55: -505 | F55: 50 | G55: 2164.45 | H55: -248.92
A56: Debt - Issued/(Reduced) - Long-Term & Short-Term - Cash Flow | B56: -148 | C56: 30 | D56: 177 | E56: -505
A57: Debt - Issued - Long-Term & Short-Term - Cash Flow | B57: 56 | C57: 313 | D57: 245
A58: Debt - Reduced - Long-Term & Short-Term - Cash Flow | B58: 204 | C58: 283 | D58: 68 | E58: 505
A59: Debt - Issued/(Reduced) - Short-Term - Total - Cash Flow | H59: -13.92
A60: Debt - Reduced - Short-Term - Cash Flow | H60: 13.92
A61: Debt - Issued/(Reduced) - Long-Term - Cash Flow | F61: 50 | G61: 2164.45 | H61: -235
A62: Debt - Issued - Long-Term - Cash Flow | F62: 262 | G62: 3153.45 | H62: 130
A63: Debt - Reduced - Long-Term - Cash Flow | F63: 212 | G63: 989 | H63: 365
A64: Other Financing Cash Flow - Increase/(Decrease) | B64: -23.22 | C64: -115.56 | D64: -19.39 | E64: -30.72 | F64: -27.04 | G64: -61.17 | H64: -62.87
A65: Net Cash Flow from Financing Activities | B65: -207.53 | C65: -159.72 | D65: 137.74 | E65: -558.97 | F65: -33.83 | G65: 2065.05 | H65: -389.39
A66: Foreign Exchange Effects
A67: Foreign Exchange Effects - Cash Flow | B67: 0.09 | C67: 0.39 | D67: 2.03 | E67: -0.22 | F67: -6.99 | G67: 2.23 | H67: 1.28
A68: Change in Cash
A69: Net Change in Cash - Total | B69: 7.53 | C69: -2.6 | D69: 349.85 | E69: -298.55 | F69: 31.21 | G69: 31.54 | H69: -8.94
A70: Net Cash from Continuing Operations | B70: 7.53 | C70: -2.6 | D70: 349.85 | E70: -298.55 | F70: 31.21 | G70: 31.54 | H70: -8.94
A71: Net Cash - Beginning Balance | B71: 52.07 | C71: 59.6 | D71: 57 | E71: 406.85 | F71: 108.3 | G71: 139.5 | H71: 171.05
A72: Net Cash - Ending Balance | B72: 59.6 | C72: 57 | D72: 406.85 | E72: 108.3 | F72: 139.5 | G72: 171.05 | H72: 162.1
A73: Supplemental
A74: Income Taxes - Paid/(Reimbursed) - Cash Flow - Supplemental | B74: 90.49 | C74: 82.21 | D74: 42.55 | E74: 67.66 | F74: 81 | G74: 138.67 | H74: 114.85
A75: Interest Paid - Cash Flow - Supplemental | B75: 19.23 | C75: 22.16 | D75: 13.42 | E75: 7.36 | F75: 6.04 | G75: 54.14 | H75: 148.9
A76: CF from Optg Activities before Change in WC & Int Payments | B76: 366.2 | C76: 456.23 | D76: 438.47 | E76: 429.78 | F76: 513.86 | G76: 552.58 | H76: 793.74
A77: Contract Assets - Decrease/(Increase) - Cash Flow | C77: 11.58 | D77: -16.4 | E77: 0.38 | F77: -4.15 | G77: -11.64 | H77: 1.29
A78: Depreciation, Depletion & Amortization - Cash Flow | B78: 77.19 | C78: 83.5 | D78: 88.56 | E78: 93.02 | F78: 96.33 | G78: 130.04 | H78: 175.33
A79: Free Cash Flow to Equity | B79: 138.62 | C79: 438.44 | D79: 563.18 | E79: -97.1 | F79: 485.87 | G79: 2563.75 | H79: 365.19
A80: Free Cash Flow Net of Dividends | B80: 271.25 | C80: 389.75 | D80: 364.63 | E80: 384.9 | F80: 411.41 | G80: 371.93 | H80: 585.04
A81: Free Cash Flow | B81: 286.62 | C81: 408.44 | D81: 386.19 | E81: 407.9 | F81: 435.87 | G81: 399.3 | H81: 614.11
A82: Dividends Provided/Paid - Common | B82: 15.36 | C82: 18.69 | D82: 21.55 | E82: 23 | F82: 73.39 | G82: 27.37 | H82: 29.07

Sheet Balance Sheet
A1: Company Fundamentals - Balance Sheet
A2: Company Name | B2: HEICO Corp (HEI)
A3: Country of Exchange | B3: United States of America
A4: Country of Headquarters | B4: United States of America
A5: TRBC Industry Group | B5: Aerospace & Defense
A6: CF Template | B6: IND
A7: Consolidation Basis | B7: Consolidated
A8: Scaling | B8: Millions
A9: Period | B9: Annual
A10: Export Date | B10: 45772.958
A11: Statement Data | B11: 2015 | C11: 2016 | D11: 2017 | E11: 2018 | F11: 2019 | G11: 2020 | H11: 2021 | I11: 2022 | J11: 2023 | K11: 2024
A12: Period End Date | B12: 42308 | C12: 42674 | D12: 43039 | E12: 43404 | F12: 43769 | G12: 44135 | H12: 44500 | I12: 44865 | J12: 45230 | K12: 45596
A13: Statement Date | B13: 42307 | C13: 43038 | D13: 43038 | E13: 43584 | F13: 43768 | G13: 44134 | H13: 44499 | I13: 44864 | J13: 45229 | K13: 45595
A14: Standardized Currency | B14: USD | C14: USD | D14: USD | E14: USD | F14: USD | G14: USD | H14: USD | I14: USD | J14: USD | K14: USD
A15: Template Type | B15: Industrial - Differentiated | C15: Industrial - Differentiated | D15: Industrial - Differentiated | E15: Industrial - Differentiated | F15: Industrial - Differentiated | G15: Industrial - Differentiated | H15: Industrial - Differentiated | I15: Industrial - Differentiated | J15: Industrial - Differentiated | K15: Industrial - Differentiated
A17: Balance Sheet - Standardized (Currency: Standardized)
A18: Field Name | B18: 30-10-2015 | C18: 30-10-2016 | D18: 30-10-2017 | E18: 30-10-2018 | F18: 30-10-2019 | G18: 30-10-2020 | H18: 30-10-2021 | I18: 30-10-2022 | J18: 30-10-2023 | K18: 30-10-2024
A19: Current Assets
A20: Cash & Short-Term Investments | B20: 33.6 | C20: 42.96 | D20: 52.07 | E20: 59.6 | F20: 57 | G20: 406.85 | H20: 108.3 | I20: 139.5 | J20: 171.05 | K20: 162.1
A21: Cash & Cash Equivalents | B21: 33.6 | C21: 42.96 | D21: 52.07 | E21: 59.6 | F21: 57 | G21: 406.85 | H21: 108.3 | I21: 139.5 | J21: 171.05 | K21: 162.1
A22: Loans & Receivables - Net - Short-Term | B22: 181.59 | C22: 202.23 | D22: 222.46 | E22: 251.47 | F22: 317.46 | G22: 270.86 | H22: 324.99 | I22: 388.83 | J22: 620.78 | K22: 650.72
A23: Trade Accounts & Trade Notes Receivable - Net | B23: 181.59 | C23: 202.23 | D23: 222.46 | E23: 237.29 | F23: 274.33 | G23: 210.43 | H23: 244.92 | I23: 294.85 | J23: 509.08 | K23: 538.49
A24: Trade Accounts & Trade Notes Receivable - Gross | B24: 183.63 | C24: 205.39 | D24: 225.46 | E24: 240.54 | F24: 277.99 | G24: 223.17 | H24: 255.79 | I24: 303.18 | J24: 521.7 | K24: 550.28
A25: Provision - Trade Accounts & Trade Notes Receivable | B25: 2.04 | C25: 3.16 | D25: 3.01 | E25: 3.26 | F25: 3.67 | G25: 12.74 | H25: 10.87 | I25: 8.33 | J25: 12.62 | K25: 11.79
A26: Receivables - Other - Total | E26: 14.18 | F26: 43.13 | G26: 60.43 | H26: 80.07 | I26: 93.98 | J26: 111.7 | K26: 112.24
A27: Inventories - Total | B27: 243.52 | C27: 286.3 | D27: 343.63 | E27: 401.55 | F27: 420.32 | G27: 463.21 | H27: 478.05 | I27: 582.47 | J27: 1013.68 | K27: 1170.95
A28: Inventories - Raw Materials | B28: 89.74 | C28: 117.15 | D28: 128.03 | E28: 158.04 | F28: 187.89 | G28: 189.75 | H28: 194.3 | I28: 237.71 | J28: 311.5 | K28: 387.26
A29: Inventories - Work in Progress | B29: 36.72 | C29: 39.33 | D29: 42.4 | E29: 50.96 | F29: 32.55 | G29: 37.96 | H29: 44.89 | I29: 59.74 | J29: 79.79 | K29: 99.11
A30: Inventories - Finished Goods | B30: 119.26 | C30: 131.01 | D30: 173.56 | E30: 192.76 | F30: 199.88 | G30: 235.5 | H30: 238.87 | I30: 285.02 | J30: 622.4 | K30: 684.58
A31: Inventories - Other - Total | B31: -2.21 | C31: -1.19 | D31: -0.36 | E31: -0.21 | F31: 0
A32: Prepaid Expenses - Short-Term | B32: 9.37 | C32: 11.67 | D32: 13.74 | E32: 21.19 | F32: 18.95 | G32: 24.71 | H32: 26.05 | I32: 41.93 | J32: 49.84 | K32: 78.52
A33: Other Current Assets - Total | B33: 35.53
A34: Deferred Tax - Asset - Short-Term | B34: 35.53
A35: Total Current Assets | B35: 503.61 | C35: 543.16 | D35: 631.89 | E35: 733.81 | F35: 813.73 | G35: 1165.63 | H35: 937.39 | I35: 1152.73 | J35: 1855.34 | K35: 2062.29
A36: Non-Current Assets
A37: Property, Plant & Equipment - Net - Total | B37: 105.67 | C37: 121.61 | D37: 129.88 | E37: 154.74 | F37: 173.35 | G37: 225.95 | H37: 268.25 | I37: 315.63 | J37: 443.22 | K37: 470.87
A38: Property, Plant & Equipment - excluding Assets Leased Out - Net - Total | B38: 105.67 | C38: 121.61 | D38: 129.88 | E38: 154.74 | F38: 173.35 | G38: 225.95 | H38: 268.25 | I38: 315.63 | J38: 443.22 | K38: 470.87
A39: Property, Plant & Equipment - Gross - Total | B39: 232.38 | C39: 266.46 | D39: 294.2 | E39: 342.44 | F39: 385.33 | G39: 458.45 | H39: 525.2 | I39: 592.71 | J39: 756.05 | K39: 827.3
A40: Property, Plant & Equipment - excluding Assets Leased Out - Gross | B40: 232.38 | C40: 266.46 | D40: 294.2 | E40: 342.44 | F40: 385.33 | G40: 458.45 | H40: 525.2 | I40: 592.71 | J40: 756.05 | K40: 827.3
A41: Land & Buildings - Gross | B41: 75.69 | C41: 84.3 | D41: 97.35 | E41: 107.29 | F41: 123.82 | G41: 127.45 | H41: 145.51 | I41: 166.18 | J41: 222.21 | K41: 237.53
A42: Land/Improvements - Gross | B42: 5.06 | C42: 5.09 | D42: 5.44 | E42: 5.86 | F42: 6.82 | G42: 6.68 | H42: 11.36 | I42: 17.58 | J42: 19.71 | K42: 19.97
A43: Buildings - Gross | B43: 70.63 | C43: 79.21 | D43: 91.92 | E43: 101.42 | F43: 117 | G43: 120.77 | H43: 134.15 | I43: 148.6 | J43: 202.5 | K43: 217.55
A44: Plant, Machinery & Equipment - Gross | B44: 152.02 | C44: 171.72 | D44: 191.3 | E44: 230.11 | F44: 253.13 | G44: 265.41 | H44: 297.3 | I44: 322.25 | J44: 386.6 | K44: 422.5
A45: Construction in Progress - Gross | B45: 4.67 | C45: 10.45 | D45: 5.55 | E45: 5.04 | F45: 8.38 | G45: 8.49 | H45: 7.78 | I45: 14.53 | J45: 25.87 | K45: 35.43
A46: Right of Use Tangible Assets - Total - Gross | G46: 57.1 | H46: 74.61 | I46: 89.75 | J46: 121.37 | K46: 131.84
A47: Right of Use Tangible Assets - Operating Lease - Gross | G47: 57.1 | H47: 74.61 | I47: 89.75 | J47: 121.37 | K47: 131.84
A48: Property, Plant & Equipment - Accumulated Depreciation & Impairment - Total | B48: 126.71 | C48: 144.85 | D48: 164.32 | E48: 187.7 | F48: 211.98 | G48: 232.49 | H48: 256.96 | I48: 277.08 | J48: 312.83 | K48: 356.43
A49: Property, Plant & Equipment - excluding Assets Leased Out - Accumulated Depreciation & Impairment - Total | B49: 126.71 | C49: 144.85 | D49: 164.32 | E49: 187.7 | F49: 211.98 | G49: 232.49 | H49: 256.96 | I49: 277.08 | J49: 312.83 | K49: 356.43
A50: Other Non-Current Assets - Total | B50: 87.87 | C50: 101.06 | D50: 131.27 | E50: 143.66 | F50: 162.74 | G50: 193.93 | H50: 260.07 | I50: 221.38 | J50: 264.89 | K50: 344.59
A51: Deferred Tax - Asset - Long-Term | B51: 0.85 | C51: 0.41 | D51: 0
A52: Other Non-Current Assets | B52: 87.03 | C52: 100.66 | D52: 131.27 | G52: 193.93 | H52: 260.07 | I52: 221.38 | J52: 264.89 | K52: 344.59
A53: Intangible Assets - Total - Net | B53: 1039.23 | C53: 1232.58 | D53: 1619.39 | E53: 1621.19 | F53: 1819.4 | G53: 1962.21 | H53: 2032.7 | I53: 2405.75 | J53: 4631.61 | K53: 4715.07
A54: Goodwill/Cost in Excess of Assets Purchased - Net | B54: 766.64 | C54: 865.72 | D54: 1081.31 | E54: 1114.83 | F54: 1268.7 | G54: 1383.17 | H54: 1450.4 | I54: 1672.43 | J54: 3274.33 | K54: 3380.3
A55: Intangible Assets - excluding Goodwill - Net - Total | B55: 272.59 | C55: 366.86 | D55: 538.08 | E55: 506.36 | F55: 550.69 | G55: 579.04 | H55: 582.31 | I55: 733.33 | J55: 1357.28 | K55: 1334.77
A56: Brands, Patents, Trademarks, Marketing & Artistic Intangibles - Net | B56: 68.06 | C56: 96.66 | D56: 134.6 | E56: 134.81 | F56: 153.69 | G56: 166.89 | H56: 176.71 | I56: 215.05 | J56: 289.17 | K56: 293.26
A57: Licenses, Franchises, Copyrights, Property Rights, Prototypes, Contract Based, Models & Designs - Net | B57: 77.55 | C57: 110.76 | D57: 140.58 | E57: 132.97 | F57: 148.65 | G57: 157.93 | H57: 162.19 | I57: 185.19 | J57: 326.83 | K57: 334.33
A58: Intangible Assets - Other - Net | B58: 126.99 | C58: 159.44 | D58: 262.9 | E58: 238.59 | F58: 248.35 | G58: 254.22 | H58: 243.41 | I58: 333.09 | J58: 741.28 | K58: 707.18
A59: Total Non-Current Assets | B59: 1232.78 | C59: 1455.25 | D59: 1880.54 | E59: 1919.59 | F59: 2155.48 | G59: 2382.09 | H59: 2561.02 | I59: 2942.77 | J59: 5339.72 | K59: 5530.53
A60: Total Assets
A61: Total Assets | B61: 1736.39 | C61: 1998.41 | D61: 2512.43 | E61: 2653.4 | F61: 2969.21 | G61: 3547.71 | H61: 3498.41 | I61: 4095.5 | J61: 7195.06 | K61: 7592.82
A62: Current Liabilities
A63: Trade Accounts Payable & Accruals - Short-Term | B63: 164.84 | C63: 159.79 | D63: 188.24 | E63: 278.73 | F63: 237.3 | G63: 175.11 | H63: 219.98 | I63: 294.18 | J63: 468.32 | K63: 510.45
A64: Trade Accounts & Trade Notes Payable - Short-Term | B64: 64.68 | C64: 73.33 | D64: 89.72 | E64: 107.22 | F64: 106.23 | G64: 76.24 | H64: 85.54 | I64: 116.55 | J64: 205.89 | K64: 198.43
A65: Accrued Expenses - Short-Term | B65: 100.16 | C65: 86.46 | D65: 98.51 | E65: 171.51 | F65: 131.08 | G65: 98.87 | H65: 134.44 | I65: 177.62 | J65: 262.42 | K65: 312.02
A66: Short-Term Debt & Current Portion of Long-Term Debt | B66: 0.36 | C66: 0.41 | D66: 0.45 | E66: 0.86 | F66: 0.91 | G66: 1.05 | H66: 1.52 | I66: 1.65 | J66: 17.8 | K66: 4.11
A67: Current Portion of Long-Term Debt including Capitalized Leases | B67: 0.36 | C67: 0.41 | D67: 0.45 | E67: 0.86 | F67: 0.91 | G67: 1.05 | H67: 1.52 | I67: 1.65 | J67: 17.8 | K67: 4.11
A68: Current Portion of Long-Term Debt excluding Capitalized Leases | D68: 0 | G68: 0.01 | H68: 0.03 | I68: 0.03 | J68: 13.55 | K68: 0.05
A69: Capitalized Leases - Current Portion | C69: 0.41 | D69: 0.45 | G69: 1.03 | H69: 1.48 | I69: 1.62 | J69: 4.25 | K69: 4.06
A70: Income Taxes - Payable - Short-Term | B70: 3.19 | C70: 4.62 | D70: 11.65 | E70: 2.84 | F70: 3.05 | G70: 1.65 | H70: 0.96 | I70: 12.46 | J70: 8.55 | K70: 33.53
A71: Operating Lease Liabilities - Current Portion/Short-Term | G71: 14.18 | H71: 13.87 | I71: 14.66 | J71: 20.5 | K71: 23.42
A72: Other Current Liabilities - Total | C72: 49.59 | D72: 49.1 | F72: 47.88 | G72: 49.18 | H72: 58.55 | I72: 97.92 | J72: 150.17 | K72: 92.34
A73: Deferred Income - Short-Term | C73: 32.14 | D73: 29.25 | F73: 23.81 | G73: 25.63 | H73: 32.74 | I73: 58.76 | J73: 87.56 | K73: 83.9
A74: Billings in Excess of Cost - Short-Term | C74: 11.01 | D74: 1.25
A75: Other Current Liabilities | C75: 6.45 | D75: 18.61 | F75: 24.07 | G75: 23.55 | H75: 25.81 | I75: 39.16 | J75: 62.62 | K75: 8.44
A76: Total Current Liabilities | B76: 168.39 | C76: 214.42 | D76: 249.44 | E76: 282.43 | F76: 289.14 | G76: 241.16 | H76: 294.88 | I76: 420.86 | J76: 665.34 | K76: 663.85
A77: Non-Current Liabilities
A78: Debt - Long-Term - Total | B78: 367.24 | C78: 457.81 | D78: 673.53 | E78: 531.61 | F78: 561.05 | G78: 738.79 | H78: 234.98 | I78: 288.62 | J78: 2460.28 | K78: 2225.27
A79: Long-Term Debt excluding Capitalized Leases | B79: 367.24 | C79: 457.81 | D79: 671.12 | E79: 531.61 | F79: 553.32 | G79: 730.25 | H79: 225.22 | I79: 275.24 | J79: 2436.71 | K79: 2203.47
A80: Debt - Non-Convertible - Long-Term | B80: 367.24 | C80: 457.81 | D80: 671.12 | E80: 531.61 | F80: 553.32 | G80: 730.25 | H80: 225.22 | I80: 275.24 | J80: 2436.71 | K80: 2203.47
A81: Capitalized Lease Obligations - Long-Term | D81: 2.41 | F81: 7.73 | G81: 8.53 | H81: 9.76 | I81: 13.38 | J81: 23.56 | K81: 21.8
A82: Deferred Tax & Investment Tax Credits - Long-Term | B82: 110.59 | C82: 64.9 | D82: 59.03 | E82: 46.64 | F82: 51.5 | G82: 55.66 | H82: 40.76 | I82: 71.16 | J82: 131.85 | K82: 114.16
A83: Deferred Tax - Liability - Long-Term | B83: 110.59 | C83: 64.9 | D83: 59.03 | E83: 46.64 | F83: 51.5 | G83: 55.66 | H83: 40.76 | I83: 71.16 | J83: 131.85 | K83: 114.16
A84: Operating Lease Liabilities - Long-Term | G84: 44.11 | H84: 61.83 | I84: 76.97 | J84: 104.76 | K84: 113.46
A85: Other Non-Current Liabilities - Total | B85: 105.62 | C85: 114.06 | D85: 151.03 | E85: 157.66 | F85: 184.6 | G85: 236.18 | H85: 316.43 | I85: 261.98 | J85: 274.88 | K85: 412.53
A86: Deferred Revenue - Long-Term | K86: 61.84
A87: Other Non-Current Liabilities | B87: 105.62 | C87: 114.06 | D87: 151.03 | E87: 157.66 | F87: 184.6 | G87: 236.18 | H87: 316.43 | I87: 261.98 | J87: 274.88 | K87: 350.69
A88: Minority Interest - Non-Equity | B88: 91.28 | C88: 99.51 | D88: 131.12 | E88: 132.05 | F88: 188.26 | G88: 221.21 | H88: 252.59 | I88: 327.6 | J88: 364.81 | K88: 366.16
A89: Total Non-Current Liabilities | B89: 674.73 | C89: 736.29 | D89: 1014.7 | E89: 867.96 | F89: 985.41 | G89: 1295.94 | H89: 906.59 | I89: 1026.33 | J89: 3336.57 | K89: 3231.57
A90: Total Liabilities
A91: Total Liabilities | B91: 843.12 | C91: 950.71 | D91: 1264.14 | E91: 1150.39 | F91: 1274.55 | G91: 1537.1 | H91: 1201.47 | I91: 1447.19 | J91: 4001.91 | K91: 3895.42
A92: Shareholders' Equity
A93: Shareholders' Equity - Attributable to Parent Shareholders - Total | B93: 809.86 | C93: 963.38 | D93: 1161.08 | E93: 1398.25 | F93: 1666.54 | G93: 1980.18 | H93: 2263.07 | I93: 2606.14 | J93: 3146 | K93: 3636.88
A94: Preferred Shareholders Equity | E94: 0 | F94: 0 | G94: 0 | H94: 0 | J94: 0
A95: Preferred Stock - Non-Redeemable | E95: 0 | F95: 0 | G95: 0 | H95: 0 | J95: 0
A96: Common Equity Attributable to Parent Shareholders | B96: 809.86 | C96: 963.38 | D96: 1161.08 | E96: 1398.25 | F96: 1666.54 | G96: 1980.18 | H96: 2263.07 | I96: 2606.14 | J96: 3146 | K96: 3636.88
A97: Common Equity - Contributed | B97: 286.89 | C97: 307 | D97: 327.39 | E97: 322.32 | F97: 285.95 | G97: 301.28 | H97: 322.1 | I97: 398.7 | J97: 580.19 | K97: 600.79
A98: Common Stock - Issued & Paid | B98: 0.67 | C98: 0.67 | D98: 0.85 | E98: 1.33 | F98: 1.35 | G98: 1.35 | H98: 1.36 | I98: 1.37 | J98: 1.38 | K98: 1.39
A99: Common Stock - Additional Paid in Capital including Option Reserve | B99: 286.22 | C99: 306.33 | D99: 326.54 | E99: 320.99 | F99: 284.61 | G99: 299.93 | H99: 320.75 | I99: 397.34 | J99: 578.81 | K99: 599.4
A100: Equity - Non-Contributed - Reserves & Retained Earnings | B100: 522.97 | C100: 656.38 | D100: 833.69 | E100: 1075.93 | F100: 1380.59 | G100: 1678.9 | H100: 1940.97 | I100: 2207.43 | J100: 2565.8 | K100: 3036.09
A101: Retained Earnings - Total | B101: 548.05 | C101: 681.7 | D101: 844.25 | E101: 1091.18 | F101: 1397.33 | G101: 1688.05 | H101: 1949.52 | I101: 2253.93 | J101: 2605.98 | K101: 3062.17
...

Sheet CFS
A4: x | B4: Cash Flow Statement
B5: in $millions, unless otherwise specified
B7: Fiscal year ending December 31, | C7: =2015 | D7: =C7+1 | E7: =D7+1 | F7: =E7+1 | G7: =F7+1 | H7: =G7+1 | I7: =H7+1 | J7: =I7+1 | K7: =J7+1 | ... P7: =O7+1
B9: CFO
B10: Net income | C10: 11.768 | D10: 10.154 | E10: 29.251 | F10: 21.524 | G10: 53.33 | H10: 8.094 | I10: =IS!I33 | J10: =IS!J33 | K10: =IS!K33 | L10: =IS!L33 | M10: =IS!M33 | N10: =IS!N33 | O10: =IS!O33 | P10: =IS!P33
B11: Changes in operating assets and liabilities, net of acquisitions: | C11: 0.276 | D11: 0.648 | E11: 0.453 | F11: 0.149 | G11: 1.17 | I11: -0.775 | J11: 1.156
B12: Accounts receivable | C12: 1.559 | D12: 2.071 | E12: 2.055 | F12: 0.273 | G12: -0.123 | H12: -2.587 | I12: 2.494 | J12: -1.029
B13: Inventory | F13: 3.319 | G13: -3.272 | H13: -55.275 | I13: -0.009 | J13: -37.637
B14: Deposits, prepaid expenses, and other current assets | H14: 3.374 | I14: 0.448 | J14: 2.923
B15: Deferred customer incentives and other assets | C15: 0.391 | D15: 0.786 | E15: 0.965 | F15: 0.9 | G15: 0.7 | H15: 0.056 | I15: 1.24 | J15: 0.893
B16: Advance vendor payments | C16: 5.808 | D16: 6.49 | E16: 17.734 | F16: 21.721 | G16: 22.134 | H16: -2.958 | I16: 29.715 | J16: -13.298
B17: Accounts payable | C17: 0.108 | D17: 0.103 | E17: 0.097 | F17: 0.108 | G17: 0.108 | H17: -0.801 | I17: 15.823 | J17: 1.164
B18: Income tax receivable | G18: 7.6 | H18: 0 | I18: 9.692 | J18: 0
B19: Income tax payable | H19: 1.324 | J19: -3.443
B20: Accrued expenses | H20: -1.697 | J20: 0.417
B21: Deferred revenue | C21: -3.552 | D21: -4.837 | E21: 2.488 | F21: -11.482 | G21: 2.599 | H21: -5.894 | I21: -10.115 | J21: -1.505
B22: Lessee and customer purchase deposits | H22: 1.776 | J22: -18.027
B23: Other liabilities | C23: -0.47 | D23: -0.23 | G23: -0.198 | H23: -0.957 | J23: -2.523
B24: Maintenance deposit payments and other liabilities | H24: 0 | J24: 0
B25: Net cash provided by operating activities | C25: 0.681 | D25: 0.081 | E25: 0.12 | H25: 0 | J25: 0
B26: Cash flows from investing activities: | C26: 3.347 | D26: 4.001 | E26: 7.413 | F26: 13.429 | G26: 20.603 | I26: 38.694 | J26: 0
B27: Business acquisitions | H27: -16.976 | I27: 0.185 | J27: 0
A28: 1000 | B28: Proceeds from sale of assets | E28: 0.828 | F28: 1.41 | H28: 3.1 | J28: 52.771
B29: Proceeds from legal settlement, net | G29: -6.931 | H29: 0 | J29: 4.195
B30: Acquisition of aircraft and engines held for lease, including capitalized cost | G30: 0.85 | H30: -5.128 | I30: -2.383 | J30: -7.133
B31: Purchase of property and equipment | G31: 0.605 | H31: -2.137 | I31: -1.508 | J31: -8.462
B32: Net cash provided by (used in) investing activities | H32: -21.141 | J32: 41.371
B34: Net Change in Cash Balance | C34: =SUM(#REF!,#REF!,#REF!) | D34: =SUM(#REF!,#REF!,#REF!) | E34: =SUM(#REF!,#REF!,#REF!) | F34: =SUM(#REF!,#REF!,#REF!) | G34: =SUM(#REF!,#REF!,#REF!) | H34: =SUM(#REF!,#REF!,#REF!) | I34: =SUM(#REF!,#REF!,#REF!) | J34: =SUM(#REF!,#REF!,#REF!)
B36: Beginning Cash Balance
B37: Ending Cash Balance
B39: Cash paid for interest | C39: 0.175 | D39: 0.181 | E39: 2.01 | F39: 2.695 | G39: 2.73 | H39: 2.427 | I39: 0.114 | J39: 0
B40: Cash paid for income taxes, net of refunds | C40: 8.508 | D40: 6.021 | E40: 1.805 | F40: -2.052 | G40: 2.254 | H40: 7.369 | I40: 4.146 | J40: 7.453

Sheet IS
A5: x | B5: Income Statement
B6: in $millions, unless otherwise specified
B8: Fiscal year ending December 31, | C8: =2015 | D8: =C8+1 | E8: =D8+1 | F8: =E8+1 | G8: =F8+1 | H8: =G8+1 | I8: =H8+1 | J8: =I8+1 | K8: =J8+1 | ... P8: =O8+1
B9: Aircraft | C9: 140.936 | D9: 173.54 | E9: 236.283 | F9: 291.072 | G9: 337.375 | H9: 53.639 | I9: 87.461 | J9: 101.511 | K9: ='Costs & Expenses Build'!F13 | L9: ='Costs & Expenses Build'!G13 | M9: ='Costs & Expenses Build'!H13 | N9: ='Costs & Expenses Build'!I13 | O9: ='Costs & Expenses Build'!J13 | P9: ='Costs & Expenses Build'!#REF!
B10: Engines | H10: 45.072 | I10: 144.549 | J10: 176.096
B11: Total Assem Management Solutions Revenue | H11: =SUM(H9:H10) | I11: =SUM(I9:I10) | J11: =SUM(J9:J10)
B12: MRO | H12: 103.899 | I12: 99.899 | J12: 95.258
B13: Product Sales | H13: 6.328 | I13: 8.528 | J13: 11.942
B14: Whole Asset Sale | C14: 67.952 | D14: 87.566 | E14: 102.654 | F14: 129.422 | G14: 164.988 | H14: 0 | I14: 0 | J14: 23.737 | K14: ='Costs & Expenses Build'!F11 | L14: ='Costs & Expenses Build'!G11 | M14: ='Costs & Expenses Build'!H11 | N14: ='Costs & Expenses Build'!I11 | O14: ='Costs & Expenses Build'!J11 | P14: ='Costs & Expenses Build'!#REF!
B15: Total TechOps Revenue | H15: =SUM(H12:H14) | I15: =SUM(I12:I14) | J15: =SUM(J12:J14)
A16: x | B16: Total revenue | C16: =SUM(C9:C14) | D16: =SUM(D9:D14) | E16: =SUM(E9:E14) | F16: =SUM(F9:F14) | G16: =SUM(G9:G14) | H16: =SUM(H11,H15) | I16: =SUM(I11,I15) | J16: =SUM(J11,J15) | K16: =SUM(K9:K14) | L16: =SUM(L9:L14) | M16: =SUM(M9:M14) | N16: =SUM(N9:N14) | O16: =SUM(O9:O14) | P16: =SUM(P9:P14)
B17: Cost of Product | C17: 25.722 | D17: 30.229 | E17: 35.61 | F17: 44.933 | G17: 50.066 | H17: 49.89 | I17: 139.475 | J17: 176.074 | K17: ='Costs & Expenses Build'!F28 | L17: ='Costs & Expenses Build'!G28 | M17: ='Costs & Expenses Build'!H28 | N17: ='Costs & Expenses Build'!I28 | O17: ='Costs & Expenses Build'!J28 | P17: ='Costs & Expenses Build'!#REF!
B18: Cost of Leasing | C18: 25.722 | D18: 30.229 | E18: 35.61 | F18: 44.933 | G18: 50.066 | H18: 24.244 | I18: 9.804 | J18: 6.929 | K18: ='Costs & Expenses Build'!#REF! | L18: ='Costs & Expenses Build'!#REF! | M18: ='Costs & Expenses Build'!#REF! | N18: ='Costs & Expenses Build'!#REF! | O18: ='Costs & Expenses Build'!#REF! | P18: ='Costs & Expenses Build'!#REF!
B19: Cost of Services | C19: 51.652 | D19: 69.151 | E19: 80.578 | F19: 100.782 | G19: 133.533 | H19: 82.015 | I19: 71.766 | J19: 74.147 | K19: ='Costs & Expenses Build'!F23 | L19: ='Costs & Expenses Build'!G23 | M19: ='Costs & Expenses Build'!H23 | N19: ='Costs & Expenses Build'!I23 | O19: ='Costs & Expenses Build'!J23 | P19: ='Costs & Expenses Build'!#REF!
A20: x | B20: Total cost of revenue | C20: =SUM(C18:C19) | D20: =SUM(D18:D19) | E20: =SUM(E18:E19) | F20: =SUM(F18:F19) | G20: =SUM(G18:G19) | H20: =SUM(H17:H19) | I20: =SUM(I17:I19) | J20: =SUM(J17:J19) | K20: =SUM(K18:K19) | L20: =SUM(L18:L19) | M20: =SUM(M18:M19) | N20: =SUM(N18:N19) | O20: =SUM(O18:O19) | P20: =SUM(P18:P19)
B21: Sales, general, and administrative | C21: 32.24 | D21: 38.98 | E21: 43.49 | F21: 55.902 | G21: 61.815 | H21: 55.635 | I21: 77.498 | J21: 96.348 | K21: ='Costs & Expenses Build'!F31 | L21: ='Costs & Expenses Build'!G31 | M21: ='Costs & Expenses Build'!H31 | N21: ='Costs & Expenses Build'!I31 | O21: ='Costs & Expenses Build'!J31 | P21: ='Costs & Expenses Build'!#REF!
B22: Paroll support program proceeds | C22: 40.002 | D22: 44.272 | E22: 72.755 | F22: 89.204 | G22: 114.443 | H22: -12.693 | I22: -14.768 | K22: ='Costs & Expenses Build'!F37 | L22: ='Costs & Expenses Build'!G37 | M22: ='Costs & Expenses Build'!H37 | N22: ='Costs & Expenses Build'!I37 | O22: ='Costs & Expenses Build'!J37 | P22: ='Costs & Expenses Build'!#REF!
B23: transactio cost recovered | C23: 5.808 | D23: 6.49 | E23: 17.734 | F23: 21.721 | G23: 22.134 | H23: -1.436 | K23: ='Costs & Expenses Build'!F43 | L23: ='Costs & Expenses Build'!G43 | M23: ='Costs & Expenses Build'!H43 | N23: ='Costs & Expenses Build'!I43 | O23: ='Costs & Expenses Build'!J43 | P23: ='Costs & Expenses Build'!#REF!
B24: Operating lease amortization
A25: x | B25: Total operating expenses | C25: =SUM(C21:C24) | D25: =SUM(D21:D24) | E25: =SUM(E21:E24) | F25: =SUM(F21:F24) | G25: =SUM(G21:G24) | H25: =SUM(H21:H24) | I25: =SUM(I21:I24) | J25: =SUM(J21:J24) | ... P25: =SUM(P21:P24)
A26: x | B26: Operating income | C26: =C16-C20-C25 | D26: =D16-D20-D25 | E26: =E16-E20-E25 | F26: =F16-F20-F25 | G26: =G16-G20-G25 | H26: =H16-H20-H25 | I26: =I16-I20-I25 | J26: =J16-J20-J25 | ... P26: =P16-P20-P25
B27: Interest income, net | C27: 0 | D27: 0 | E27: 0 | F27: 0 | G27: 4.922 | H27: -1.645 | I27: -0.98 | J27: 1.093 | K27: 0 | L27: 0 | M27: 0 | N27: 0 | O27: 0 | P27: 0
B28: Other income, net | C28: 0 | D28: 0 | E28: 0 | F28: 0 | G28: 4.922 | H28: 0.494 | I28: 0.458 | J28: 2.268 | K28: 0 | L28: 0 | M28: 0 | N28: 0 | O28: 0 | P28: 0
B29: Unrealized loss on investment | C29: 0 | D29: 0 | E29: 0 | F29: 0 | G29: 4.922 | I29: -5.421 | K29: 0 | L29: 0 | M29: 0 | N29: 0 | O29: 0 | P29: 0
B30: Change in fair value of warrant liability | C30: 0 | D30: 0 | E30: 0 | F30: 0 | G30: 4.922 | H30: -0.388 | I30: -2.945 | J30: -0.525 | K30: 0 | L30: 0 | M30: 0 | N30: 0 | O30: 0 | P30: 0
B31: Income before income taxes | C31: =C26+SUM(C30:C30) | D31: =D26+SUM(D30:D30) | E31: =E26+SUM(E30:E30) | F31: =F26+SUM(F30:F30) | G31: =G26+SUM(G30:G30) | H31: =H26+SUM(H27:H30) | I31: =I26+SUM(I27:I30) | J31: =J26+SUM(J27:J30) | K31: =K26+SUM(K30:K30) | L31: =L26+SUM(L30:L30) | M31: =M26+SUM(M30:M30) | N31: =N26+SUM(N30:N30) | O31: =O26+SUM(O30:O30) | P31: =P26+SUM(P30:P30)
B32: Provision for income taxes | C32: 5.697 | D32: 4.227 | E32: 2.99 | F32: -9.825 | G32: 5.566 | H32: 1.65 | I32: 11.659 | J32: 14.021 | K32: =K31*0.21 | L32: =L31*0.21 | M32: =M31*0.21 | N32: =N31*0.21 | O32: =O31*0.21 | P32: =P31*0.21
A33: x | B33: Net income | C33: =C31-C32 | D33: =D31-D32 | E33: =E31-E32 | F33: =F31-F32 | G33: =G31-G32 | H33: =H31-H32 | I33: =I31-I32 | J33: =J31-J32 | ... P33: =P31-P32
B34: Dividends paid on redeemable convertible preferred stock
B35: Net loss attributable to redeemable noncontrolling interest | G35: 0.201
B36: Cumulative dividend on redeemable convertible preferred stock
B37: Dividends paid to participating securities | C37: -18.987
B38: Income allocated to participating securities | C38: 0 | D38: -0.012 | E38: -0.013 | F38: -0.003
A39: x | B39: Net income attributable to common stockholders | C39: =C33+SUM(C34:C38) | D39: =D33+SUM(D34:D38) | E39: =E33+SUM(E34:E38) | F39: =F33+SUM(F34:F38) | G39: =G33+SUM(G34:G38) | H39: =H33+SUM(H34:H38) | I39: =I33+SUM(I34:I38) | J39: =J33+SUM(J34:J38) | K39: =K33-SUM(K34:K38) | L39: =L33-SUM(L34:L38) | M39: =M33-SUM(M34:M38) | N39: =N33-SUM(N34:N38) | O39: =O33-SUM(O34:O38) | P39: =P33-SUM(P34:P38)

Sheet BS
A4: x | B4: Balance Sheet
B5: in $millions, unless otherwise specified
B7: Fiscal year ending December 31, | C7: =2015 | D7: =C7+1 | E7: =D7+1 | F7: =E7+1 | G7: =F7+1 | H7: =G7+1 | I7: =H7+1 | J7: =I7+1 | K7: =J7+1 | ... AD7: =AC7+1
B9: Assets | D9: Current Assets | E9: Current Assets | F9: Current Assets | G9: Current Assets
B10: Current assets: | D10: 140.634 | E10: 96.329 | F10: 146.061 | G10: 119.629 | Z10: =CFS!#REF! | AA10: =CFS!#REF! | AB10: =CFS!#REF! | AC10: =CFS!#REF! | AD10: =CFS!#REF!
B11: Cash and cash equivalents | C11: 17505002 | D11: 29.81 | E11: 40.634 | F11: 49.51 | G11: 76.373 | H11: 2.9317 | I11: 130.188 | J11: 147.188 | Z11: =(('Costs & Expenses Build'!#REF!/365)*'Costs & Expenses Build'!#REF!) | AA11: =(('Costs & Expenses Build'!#REF!/365)*'Costs & Expenses Build'!#REF!) | AB11: =(('Costs & Expenses Build'!#REF!/365)*'Costs & Expenses Build'!#REF!) | AC11: =(('Costs & Expenses Build'!#REF!/365)*'Costs & Expenses Build'!#REF!) | AD11: =(('Costs & Expenses Build'!#REF!/365)*'Costs & Expenses Build'!#REF!)
B12: Accounts receivable, net of allowance for doubtful accounts of $1,652,000 and $1,545,000 as of December 31, 2020 and 2019 | C12: 51867653 | D12: 10.543 | E12: 14.177 | F12: 22.99 | G12: 34.168 | H12: 50.215 | I12: 42.571 | J12: 28.273 | Z12: =(('Costs & Expenses Build'!#REF!/365)*'Costs & Expenses Build'!#REF!) | AA12: =(('Costs & Expenses Build'!#REF!/365)*'Costs & Expenses Build'!#REF!) | AB12: =(('Costs & Expenses Build'!#REF!/365)*'Costs & Expenses Build'!#REF!) | AC12: =(('Costs & Expenses Build'!#REF!/365)*'Costs & Expenses Build'!#REF!) | AD12: =(('Costs & Expenses Build'!#REF!/365)*'Costs & Expenses Build'!#REF!)
B13: Inventory: | I13: 0 | J13: 0 | Z13: =Y13 | AA13: =Z13 | AB13: =AA13 | AC13: =AB13 | AD13: =AC13
B14: Aircraft, airframes, engines, and parts, net | C14: 57918723 | D14: 9.197 | E14: 12.796 | F14: 9.502 | G14: 13.504 | H14: 85.192 | I14: 81.759 | J14: 117.488 | Z14: ='Costs & Expenses Build'!#REF! | AA14: ='Costs & Expenses Build'!#REF! | AB14: ='Costs & Expenses Build'!#REF! | AC14: ='Costs & Expenses Build'!#REF! | AD14: ='Costs & Expenses Build'!#REF!
B15: Advance vendor payments | C15: 3247255 | D15: =SUM(D10:D14) | E15: =SUM(E10:E14) | F15: =SUM(F10:F14) | G15: =SUM(G10:G14) | H15: 6.205 | I15: 14.287 | J15: 27.585 | Z15: =SUM(Z10:Z14) | AA15: =SUM(AA10:AA14) | AB15: =SUM(AB10:AB14) | AC15: =SUM(AC10:AC14) | AD15: =SUM(AD10:AD14)
B16: Due from related party | C16: 6130990 | H16: 0.474 | I16: 0 | J16: 0
B17: Deposits, prepaid expenses, and other current assets | C17: 5116175 | H17: 7.56 | I17: 2.724 | J17: 13.022
B18: Total current assets | C18: 141785798 | D18: 20.18 | E18: 23.459 | F18: 27.757 | G18: 38.548 | H18: 178.963 | I18: 271.529 | J18: 333.556 | Z18: =#REF! | AA18: =#REF! | AB18: =#REF! | AC18: =#REF! | AD18: =#REF!
B19: Fixed assets: | D19: 4.568 | E19: 94.286 | F19: 79.067 | G19: 103.438 | I19: 0 | J19: 0 | Z19: =#REF! | AA19: =#REF! | AB19: =#REF! | AC19: =#REF! | AD19: =#REF!
B20: Aircraft and engines held for lease, net | C20: 111896294 | D20: 24.723 | E20: 63.591 | F20: 63.591 | G20: 104.963 | H20: 86.844 | I20: 73.364 | J20: 31.288 | Z20: =Y20 | AA20: =Z20 | AB20: =AA20 | AC20: =AB20 | AD20: =AC20
B21: Property and equipment, net | C21: 7461792 | D21: 16.752 | E21: 18.444 | F21: 28.952 | G21: 19.137 | H21: 7.839 | I21: 7.35 | J21: 12.638 | Z21: =Y21 | AA21: =Z21 | AB21: =AA21 | AC21: =AB21 | AD21: =AC21
B22: Inventory: | G22: 30.523 | I22: 0 | J22: 0 | Z22: =#REF! | AA22: =#REF! | AB22: =#REF! | AC22: =#REF! | AD22: =#REF!
B23: Aircraft, airframes, engines, and parts, net | C23: 37043804 | D23: 4.838 | E23: 7.925 | F23: 13.555 | G23: 17.516 | H23: 55.463 | I23: 77.534 | J23: 66.042 | Z23: =#REF! | AA23: =#REF! | AB23: =#REF! | AC23: =#REF! | AD23: =#REF!
B24: Operating lease right-of-use assets | D24: =SUM(D18:D23) | E24: =SUM(E18:E23) | F24: =SUM(F18:F23) | G24: =SUM(G18:G23) | I24: 0 | J24: 31.624 | Z24: =SUM(Z18:Z23) | AA24: =SUM(AA18:AA23) | AB24: =SUM(AB18:AB23) | AC24: =SUM(AC18:AC23) | AD24: =SUM(AD18:AD23)
B25: Deferred income taxes | C25: 4753679 | D25: =D15+D24 | E25: =E15+E24 | F25: =F15+F24 | G25: =G15+G24 | H25: 5.708 | I25: 10.013 | J25: 11.287 | Z25: =SUM(Z24,Z15) | AA25: =SUM(AA24,AA15) | AB25: =SUM(AB24,AB15) | AC25: =SUM(AC24,AC15) | AD25: =SUM(AD24,AD15)
B26: Deferred financing costs, net | C26: 1034564 | H26: 0.367 | I26: 0.999 | J26: 0.544
B27: Deferred customer incentives and other assets, net | C27: 324869 | H27: 0.271 | I27: 0.598 | J27: 0.628
B28: Due from related party | C28: 5449739 | D28: 18.289 | E28: 17.008 | F28: 20.214 | G28: 32.878 | H28: 5.45 | I28: 0 | J28: 0 | Z28: =('Costs & Expenses Build'!#REF!/365)*'Costs & Expenses Build'!#REF! | AA28: =('Costs & Expenses Build'!#REF!/365)*'Costs & Expenses Build'!#REF! | AB28: =('Costs & Expenses Build'!#REF!/365)*'Costs & Expenses Build'!#REF! | AC28: =('Costs & Expenses Build'!#REF!/365)*'Costs & Expenses Build'!#REF! | AD28: =('Costs & Expenses Build'!#REF!/365)*'Costs & Expenses Build'!#REF!
B29: Goodwill | C29: 13858551 | D29: 5.298 | E29: 4.301 | F29: 34.557 | G29: 10.092 | H29: 19.86 | I29: 19.86 | J29: 19.86 | Z29: ='Costs & Expenses Build'!#REF! | AA29: ='Costs & Expenses Build'!#REF! | AB29: ='Costs & Expenses Build'!#REF! | AC29: ='Costs & Expenses Build'!#REF! | AD29: ='Costs & Expenses Build'!#REF!
B30: Other intangible assets, net | C30: 20375166 | D30: 8.814 | E30: 12.127 | F30: 13.484 | G30: 16.342 | H30: 28.364 | I30: 26.238 | J30: 24.112 | Z30: ='Costs & Expenses Build'!#REF! | AA30: ='Costs & Expenses Build'!#REF! | AB30: ='Costs & Expenses Build'!#REF! | AC30: ='Costs & Expenses Build'!#REF! | AD30: ='Costs & Expenses Build'!#REF!
B31: Total assets | C31: 343984256 | D31: 2.585 | E31: 3.292 | F31: 3.356 | G31: 3.043 | H31: 389.129 | I31: 487.485 | J31: 531.579 | Z31: ='Costs & Expenses Build'!#REF! | AA31: ='Costs & Expenses Build'!#REF! | AB31: ='Costs & Expenses Build'!#REF! | AC31: ='Costs & Expenses Build'!#REF! | AD31: ='Costs & Expenses Build'!#REF!
A32: 1000 | B32: Current liabilities: | G32: 7.683 | H32: 0 | I32: 0 | J32: 0 | Z32: =#REF! | AA32: =#REF! | AB32: =#REF! | AC32: =#REF! | AD32: =#REF!
B33: Accounts payable | C33: 17030404 | D33: 0 | E33: 0 | F33: 0 | G33: 0 | H33: 16.364 | I33: 19.967 | J33: 21.131 | Z33: =0 | AA33: =0 | AB33: =0 | AC33: =0 | AD33: =0
B34: Accrued expenses | C34: 9629084 | D34: =2.506+2.207 | E34: =2.802+4.973 | F34: =0.2+3.459 | G34: =0.141+5.616 | H34: 8.576 | I34: 8.424 | J34: 8.843 | Z34: ='Costs & Expenses Build'!#REF! | AA34: ='Costs & Expenses Build'!#REF! | AB34: ='Costs & Expenses Build'!#REF! | AC34: ='Costs & Expenses Build'!#REF! | AD34: ='Costs & Expenses Build'!#REF!
B35: Income tax payable | C35: 0 | D35: =SUM(D28:D34) | E35: =SUM(E28:E34) | F35: =SUM(F28:F34) | G35: =SUM(G28:G34) | H35: 1.324 | I35: 3.443 | J35: 0 | Z35: =SUM(Z28:Z34) | AA35: =SUM(AA28:AA34) | AB35: =SUM(AB28:AB34) | AC35: =SUM(AC28:AC34) | AD35: =SUM(AD28:AD34)
B36: Lessee and customer purchase deposits | C36: 3473921 | H36: 2.82 | I36: 33.212 | J36: 17.085
B37: Current operating lease liabilities | H37: 0 | I37: 0 | J37: 4.426
B38: Current portion of long-term debt, net | C38: 3351714 | D38: 10.04 | E38: 9.386 | F38: 7.82 | G38: 7.455 | H38: 0 | I38: 0 | J38: 0 | Z38: =Y38 | AA38: =Z38 | AB38: =AA38 | AC38: =AB38 | AD38: =AC38
B39: Deferred revenue | C39: 7708761 | H39: 2.595 | I39: 2.86 | J39: 1.355 | Z39: =#REF! | AA39: =#REF! | AB39: =#REF! | AC39: =#REF! | AD39: =#REF!
B40: Total current liabilities | C40: 41193884 | D40: 6.7 | E40: 71 | F40: 67 | G40: 63 | H40: 31.679 | I40: 67.906 | J40: 52.84
B41: Long-term lease deposits | C41: 4184874 | G41: 37.199 | H41: 1.145 | I41: 2.053 | J41: 0.152 | Z41: =#REF! | AA41: =#REF! | AB41: =#REF! | AC41: =#REF! | AD41: =#REF!
B42: Long-term operating lease liabilities | D42: 13.557 | E42: 13.925 | F42: 13.306 | G42: 7.489 | H42: 0 | I42: 0 | J42: 28.283 | Z42: =Y42 | AA42: =Z42 | AB42: =AA42 | AC42: =AB42 | AD42: =AC42
B43: Maintenance deposit payments and other liabilities | C43: 4620133 | G43: 11.21 | H43: 3.664 | I43: 3.403 | J43: 0.668 | Z43: =Y43 | AA43: =Z43 | AB43: =AA43 | AC43: =AB43 | AD43: =AC43
B44: Deferred income taxes, net | D44: =SUM(D38:D43) | E44: =SUM(E38:E43) | F44: =SUM(F38:F43) | G44: =SUM(G38:G43) | H44: 0 | I44: 1.113 | J44: 0 | Z44: =SUM(Z38:Z43) | AA44: =SUM(AA38:AA43) | AB44: =SUM(AB38:AB43) | AC44: =SUM(AC38:AC43) | AD44: =SUM(AD38:AD43)
B45: Warrant liability | D45: =D35+D44 | E45: =E35+E44 | F45: =F35+F44 | G45: =G35+G44 | H45: 1.186 | I45: 4.131 | J45: 4.656 | Z45: =SUM(Z44,Z35) | AA45: =SUM(AA44,AA35) | AB45: =SUM(AB44,AB35) | AC45: =SUM(AC44,AC35) | AD45: =SUM(AD44,AD35)
B46: Total liabilities | C46: 49998891 | H46: 37.674 | I46: 78.606 | J46: 86.599
B47: Commitments and contingencies | D47: =SUM(D11,D12,D14)-SUM(D28,D29,D30,D31,D32,D34) | E47: =SUM(E11,E12,E14)-SUM(E28,E29,E30,E31,E32,E34) | F47: =SUM(F11,F12,F14)-SUM(F28,F29,F30,F31,F32,F34) | G47: =SUM(G11,G12,G14)-SUM(G28,G29,G30,G31,G32,G34) | H47: 0 | I47: 0 | J47: 0 | Z47: =SUM(Z11,Z12,Z14)-SUM(Z28,Z29,Z30,Z31,Z32,Z34) | AA47: =SUM(AA11,AA12,AA14)-SUM(AA28,AA29,AA30,AA31,AA32,AA34) | AB47: =SUM(AB11,AB12,AB14)-SUM(AB28,AB29,AB30,AB31,AB32,AB34) | AC47: =SUM(AC11,AC12,AC14)-SUM(AC28,AC29,AC30,AC31,AC32,AC34) | AD47: =SUM(AD11,AD12,AD14)-SUM(AD28,AD29,AD30,AD31,AD32,AD34)
B48: Stockholders' equity: | H48: 0 | I48: 0 | J48: 0
B49: Common stock, $0.0001 par value. Authorized 200,000,000 shares; issued and outstanding 51,673,099 and 41,046,216 shares | C49: 529 | H49: 0.004 | I49: 0.005 | J49: 0.005
B50: Additional paid-in capital | C50: 243220709 | D50: 0.461 | E50: 0.472 | F50: 0.481 | G50: 0.487 | H50: 292.593 | I50: 313.901 | J50: 306.141 | Z50: =Y50 | AA50: =Z50 | AB50: =AA50 | AC50: =AB50 | AD50: =AC50
B51: Retained earnings | C51: 50764127 | D51: 308.697 | E51: 321.032 | F51: 341.139 | G51: 365.627 | H51: 58.858 | I51: 94.973 | J51: 138.834 | Z51: =Y51 | AA51: =Z51 | AB51: =AA51 | AC51: =AB51 | AD51: =AC51
B52: Total stockholders' equity | D52: 0 | H52: 351.455 | I52: 408.879 | J52: 444.98 | Z52: =Y52 | AA52: =Z52 | AB52: =AA52 | AC52: =AB52 | AD52: =AC52
B53: Total equity | C53: 293985365 | D53: -117.909 | E53: -88.677 | F53: -64.031 | G53: -10.463 | H53: 0 | I53: 0 | J53: 0 | Z53: =Y53+CFS!#REF!-CFS!#REF!+CFS!#REF! | AA53: =Z53+CFS!#REF!-CFS!#REF!+CFS!#REF! | AB53: =AA53+CFS!#REF!-CFS!#REF!+CFS!#REF! | AC53: =AB53+CFS!#REF!-CFS!#REF!+CFS!#REF! | AD53: =AC53+CFS!#REF!-CFS!#REF!+CFS!#REF!
B54: Total liabilities and stockholders' equity | C54: 343984256 | D54: =SUM(D50:D53) | E54: =SUM(E50:E53) | F54: =SUM(F50:F53) | G54: =SUM(G50:G53) | H54: 389.129 | I54: 487.485 | J54: 531.579 | Z54: =SUM(Z50:Z53) | AA54: =SUM(AA50:AA53) | AB54: =SUM(AB50:AB53) | AC54: =SUM(AC50:AC53) | AD54: =SUM(AD50:AD53)
B56: Model Check | C56: =C25-#REF! | D56: =D25-#REF! | E56: =E25-#REF! | F56: =F25-#REF! | G56: =G25-#REF! | H56: =H31-H54 | I56: =I31-I54 | J56: =J31-J54 | Z56: =Z25-#REF! | AA56: =AA25-#REF! | AB56: =AB25-#REF! | AC56: =AC25-#REF! | AD56: =AD25-#REF!
B58: Extra Graphing Calculations:
B59: Other current liabilities (% Revenue) | C59: =C34/IS!C16 | D59: =D34/IS!D16 | E59: =E34/IS!E16 | F59: =F34/IS!F16 | G59: =G34/IS!G16 | H59: =H34/IS!H16 | I59: =I34/IS!I16 | J59: =J34/IS!J16 | Z59: =Z34/IS!#REF! | AA59: =AA34/IS!#REF! | AB59: =AB34/IS!#REF! | AC59: =AC34/IS!#REF! | AD59: =AD34/IS!#REF!

Sheet Brinks Home Security
